{
  "postId": "52885",
  "fetchedAt": "2026-05-09T16:40:31+08:00",
  "totalCommentNum": 114,
  "totalScanned": 103,
  "expandedTopLevel": 1,
  "expansionFailed": 0,
  "truncatedTopLevel": 0,
  "items": [
    {
      "type": "reply",
      "id": 357409,
      "author": "新米练习菌",
      "authorUserId": "3194882",
      "content": "自己主页能发，点自己头像，到自己主页可以发帖。但评论区不能发图。",
      "images": [],
      "createdAt": "2025-11-04T16:33:00",
      "ipLocation": "上海市",
      "likeNum": 6,
      "parent": {
        "id": 357283,
        "userName": "wys馨儿",
        "content": "米米请教一下，在这里怎么才能发送图片或者表格？🌸",
        "images": [],
        "createdAt": "2025-11-04T16:19:36",
        "ipLocation": "福建省",
        "likeNum": 0
      },
      "replyTo": null
    },
    {
      "type": "reply",
      "id": 357433,
      "author": "新米练习菌",
      "authorUserId": "3194882",
      "content": "还是有标准的，违法违规的不能发；冒犯老大的不能发。",
      "images": [],
      "createdAt": "2025-11-04T16:33:50",
      "ipLocation": "上海市",
      "likeNum": 21,
      "parent": {
        "id": 357241,
        "userName": "那就多喜乐长安宁",
        "content": "米米跟我一起读：我自己的的账号，想发啥就发，不想发就不发，我怎么开心怎么来。",
        "images": [],
        "createdAt": "2025-11-04T16:16:58",
        "ipLocation": "广东省",
        "likeNum": 9
      },
      "replyTo": null
    },
    {
      "type": "reply",
      "id": 358459,
      "author": "新米练习菌",
      "authorUserId": "3194882",
      "content": "Excel搞的",
      "images": [],
      "createdAt": "2025-11-04T18:15:38",
      "ipLocation": "上海市",
      "likeNum": 8,
      "parent": {
        "id": 358045,
        "userName": "出乎意料",
        "content": "这啥软件搞得啊，牛掰",
        "images": [],
        "createdAt": "2025-11-04T17:28:21",
        "ipLocation": "广东省",
        "likeNum": 2
      },
      "replyTo": null
    },
    {
      "type": "reply",
      "id": 358987,
      "author": "新米练习菌",
      "authorUserId": "3194882",
      "content": "嗯，我第一眼看到的时候就特别喜欢，第一个效仿的图就是这个，一直在另一页，同步更新着，但是之前一直不敢拿出来用，怕冒犯原版。老大说这是一套经典的配色系统~",
      "images": [],
      "createdAt": "2025-11-04T19:42:00",
      "ipLocation": "上海市",
      "likeNum": 8,
      "parent": {
        "id": 358945,
        "userName": "拙拙",
        "content": "我也好喜欢E大旭日图这个配色。带点灰度却色彩分明。就像一个人，是温和但有棱角的。",
        "images": [],
        "createdAt": "2025-11-04T19:32:29",
        "ipLocation": "浙江省",
        "likeNum": 1
      },
      "replyTo": null
    },
    {
      "type": "top",
      "id": 359161,
      "author": "新米练习菌",
      "authorUserId": "3194882",
      "content": "你再看下那后面几日的发车记录和微博，都有说~",
      "images": [],
      "createdAt": "2025-11-04T20:04:50",
      "ipLocation": "上海市",
      "likeNum": 1
    },
    {
      "type": "reply",
      "id": 362881,
      "author": "新米练习菌",
      "authorUserId": "3194882",
      "content": "嗯，仓位用市值。份数是额外额外备注着的。",
      "images": [],
      "createdAt": "2025-11-05T11:38:04",
      "ipLocation": "上海市",
      "likeNum": 1,
      "parent": {
        "id": 362857,
        "userName": "Gia_Alan",
        "content": "比例和份数好像并不一致？是因为用的市值吗",
        "images": [],
        "createdAt": "2025-11-05T11:32:19",
        "ipLocation": "江苏省",
        "likeNum": 0
      },
      "replyTo": null
    }
  ]
}