{
  "postId": "54127",
  "fetchedAt": "2026-05-09T16:34:50+08:00",
  "totalCommentNum": 14,
  "totalScanned": 10,
  "expandedTopLevel": 0,
  "expansionFailed": 0,
  "truncatedTopLevel": 0,
  "items": [
    {
      "type": "top",
      "id": 408049,
      "author": "新米练习菌",
      "authorUserId": "3194882",
      "content": "【笔记20】：https://qieman.com/content/content-detail?postId=54103",
      "images": [],
      "createdAt": "2025-11-12T07:59:05",
      "ipLocation": "上海市",
      "likeNum": 8
    },
    {
      "type": "reply",
      "id": 408055,
      "author": "新米练习菌",
      "authorUserId": "3194882",
      "content": "【笔记21】：https://qieman.com/content/content-detail?postId=54121",
      "images": [],
      "createdAt": "2025-11-12T07:59:26",
      "ipLocation": "上海市",
      "likeNum": 7,
      "parent": {
        "id": 408049,
        "userName": "新米练习菌",
        "content": "【笔记20】：https://qieman.com/content/content-detail?postId=54103",
        "images": [],
        "createdAt": "2025-11-12T07:59:05",
        "ipLocation": "上海市",
        "likeNum": 8
      },
      "replyTo": null
    },
    {
      "type": "reply",
      "id": 555283,
      "author": "新米练习菌",
      "authorUserId": "3194882",
      "content": "这个也改好了，多谢",
      "images": [],
      "createdAt": "2025-11-29T18:05:48",
      "ipLocation": "上海市",
      "likeNum": 0,
      "parent": {
        "id": 516925,
        "userName": "爱吃肉肉的大发",
        "content": "新米，根据图80、81数据显示美国股票自 1900 年起年化名义回报 9.9%、实际回报 6.7%，你好像看错位啦，空了可以看看资产回报规律中股票里的举例数据。\n",
        "images": [],
        "createdAt": "2025-11-23T20:56:26",
        "ipLocation": "浙江省",
        "likeNum": 0
      },
      "replyTo": null
    }
  ]
}