{
  "id": "56209",
  "url": "https://qieman.com/content/content-detail?postId=56209",
  "richContent": "<p>根据目前的内容，我的大纲是这样安排的。</p>\n<p></p>\n<p>（思路基本源于《E学宝典》，那个非常庞大细致的，且慢小组版会简化一些，而且之后会合并过去，所以一脉相承的。）</p>\n<p></p>\n<p>因为目前只涉及到这些，就先放了这些模块，以后增添了会慢慢补上。</p>\n<p></p>\n<p>给一样都在整理资料的朋友们，参考、讨论、交流用用。</p>\n<p></p>\n<p>PS：前面就在搭这个，自己在飞书文档里手建自制的，都没发现“博导进教室了”，一般做东西做进去了，就不看手机，也不开网页的，埋头专心弄，告一段落了，才抬头。发现有朋友拍我，嗯，依旧很谢谢喊我。</p>\n<img src=\"https://cdn-community.qieman.com/56231ABF-B788-4E45-805B-2FAD231C0841.png\" />",
  "images": [],
  "audioUrl": "",
  "audioDuration": 0,
  "retweetContent": "",
  "retweetAuthor": ""
}