{
  "postId": "56617",
  "fetchedAt": "2026-05-09T16:19:41+08:00",
  "totalCommentNum": 41,
  "totalScanned": 29,
  "expandedTopLevel": 1,
  "expansionFailed": 0,
  "truncatedTopLevel": 0,
  "items": [
    {
      "type": "top",
      "id": 570547,
      "author": "新米练习菌",
      "authorUserId": "3194882",
      "content": "为了实现策略，按条件选了一圈基金，发现几个基金，虽然上面的想法没法用，但是可以替换一下正在运行网格的几个基金，效果会更好些，觉得不错，今晚继续做这方面的功课",
      "images": [],
      "createdAt": "2025-12-04T07:00:25",
      "ipLocation": "上海市",
      "likeNum": 19
    },
    {
      "type": "reply",
      "id": 570691,
      "author": "新米练习菌",
      "authorUserId": "3194882",
      "content": "说到称呼，我对老大和提起他只有\n——「E大」、「老大」、「您」。\n.\n老大喊我或者提起我\n——「一般没有称呼 直接说事说内容 不加主语的那种」、「新米」、「你」。\n.\n（突然感觉还挺日式的，脑海里都有日语对应句式可以直翻，哈哈。）",
      "images": [],
      "createdAt": "2025-12-04T08:08:23",
      "ipLocation": "上海市",
      "likeNum": 11,
      "parent": {
        "id": 570547,
        "userName": "新米练习菌",
        "content": "为了实现策略，按条件选了一圈基金，发现几个基金，虽然上面的想法没法用，但是可以替换一下正在运行网格的几个基金，效果会更好些，觉得不错，今晚继续做这方面的功课",
        "images": [],
        "createdAt": "2025-12-04T07:00:25",
        "ipLocation": "上海市",
        "likeNum": 19
      },
      "replyTo": null
    },
    {
      "type": "reply",
      "id": 570709,
      "author": "新米练习菌",
      "authorUserId": "3194882",
      "content": "你看老大那天说他在忙工作时发的表格，会有一些启发~\n然后，我因为自己小黑车网格多，会有一些自己个性化的需求条件，不一定通用。\n一般选的时候就认真挑选好的，除非觉得新找的一定更好，才会换，不然不换的。",
      "images": [],
      "createdAt": "2025-12-04T08:18:19",
      "ipLocation": "上海市",
      "likeNum": 9,
      "parent": {
        "id": 570547,
        "userName": "新米练习菌",
        "content": "为了实现策略，按条件选了一圈基金，发现几个基金，虽然上面的想法没法用，但是可以替换一下正在运行网格的几个基金，效果会更好些，觉得不错，今晚继续做这方面的功课",
        "images": [],
        "createdAt": "2025-12-04T07:00:25",
        "ipLocation": "上海市",
        "likeNum": 19
      },
      "replyTo": {
        "id": 570595,
        "userName": "E想天开06",
        "content": "想听米米说说，筛选替换的网格基金标准是什么呢？经过回测效果更好？",
        "images": []
      }
    },
    {
      "type": "reply",
      "id": 575551,
      "author": "新米练习菌",
      "authorUserId": "3194882",
      "content": "那，还有“网友”…（2025.9.12）\n老大喊大家：友友们，朋友们，兄弟集美们，博友们，同志们，宝宝，您。\n到我：网友…",
      "images": [],
      "createdAt": "2025-12-04T11:50:17",
      "ipLocation": "上海市",
      "likeNum": 2,
      "parent": {
        "id": 570547,
        "userName": "新米练习菌",
        "content": "为了实现策略，按条件选了一圈基金，发现几个基金，虽然上面的想法没法用，但是可以替换一下正在运行网格的几个基金，效果会更好些，觉得不错，今晚继续做这方面的功课",
        "images": [],
        "createdAt": "2025-12-04T07:00:25",
        "ipLocation": "上海市",
        "likeNum": 19
      },
      "replyTo": {
        "id": 572053,
        "userName": "胖菜",
        "content": "E大在公众场合说你，我印象中有：\n内个谁 (内个谁，记下点位)\n课代表(课代表可以教一下)\n有位朋友(我评论里有位朋友经常做一些关于我的各种投资计划的图表）\n评论里另外的某些朋友(这次发声超赞的！)",
        "images": []
      }
    },
    {
      "type": "reply",
      "id": 580009,
      "author": "新米练习菌",
      "authorUserId": "3194882",
      "content": "啊啊，我没有觉得不好，我只是觉得很有意思、很有趣，我当天接了然后回应了。\n我的心愿就是希望被老大看见，一直都是，为之而努力，现在已经达成了，我其实已经没有什么遗憾了，而且还远超预期的感觉，现在的每一天，都已经是“超额收益”了。",
      "images": [],
      "createdAt": "2025-12-04T19:42:48",
      "ipLocation": "上海市",
      "likeNum": 3,
      "parent": {
        "id": 570547,
        "userName": "新米练习菌",
        "content": "为了实现策略，按条件选了一圈基金，发现几个基金，虽然上面的想法没法用，但是可以替换一下正在运行网格的几个基金，效果会更好些，觉得不错，今晚继续做这方面的功课",
        "images": [],
        "createdAt": "2025-12-04T07:00:25",
        "ipLocation": "上海市",
        "likeNum": 19
      },
      "replyTo": {
        "id": 578425,
        "userName": "胖菜",
        "content": "米米你知道吗，如果有一天我也能有你这样的领悟，做出贡献让E大看见记住，单独提到我一次，\n哪怕他称我“那个笨蛋”(当然E大绝对不会在网上这么称呼别人，我只是打比方。)\n我也要高兴得原地蹦起来。\n类似于郑板桥自称“青藤门下走狗”。\n我也想啊！但我不敢自称“门下”，还太远了。\n",
        "images": []
      }
    },
    {
      "type": "reply",
      "id": 580021,
      "author": "新米练习菌",
      "authorUserId": "3194882",
      "content": "美股真的，难怪 buy and hold啊~",
      "images": [],
      "createdAt": "2025-12-04T19:43:43",
      "ipLocation": "上海市",
      "likeNum": 2,
      "parent": {
        "id": 579919,
        "userName": "DragonL915",
        "content": "我最近也回测了美股最简单的均线策略，发现竟然没有一直持有效果好，跟我刚开始的想法有些出入，正在研究为什么",
        "images": [],
        "createdAt": "2025-12-04T19:07:28",
        "ipLocation": "上海市",
        "likeNum": 0
      },
      "replyTo": null
    },
    {
      "type": "reply",
      "id": 585691,
      "author": "新米练习菌",
      "authorUserId": "3194882",
      "content": "那个朱印盖章，我居然有两个，WB一个，GZH一个",
      "images": [],
      "createdAt": "2025-12-05T13:28:49",
      "ipLocation": "上海市",
      "likeNum": 1,
      "parent": {
        "id": 582217,
        "userName": "无-",
        "content": "还有签名“是真爱了”😊",
        "images": [],
        "createdAt": "2025-12-05T10:02:16",
        "ipLocation": "北京市",
        "likeNum": 0
      },
      "replyTo": null
    }
  ]
}