{
  "postId": "60025",
  "fetchedAt": "2026-05-09T15:50:40+08:00",
  "totalCommentNum": 543,
  "totalScanned": 486,
  "expandedTopLevel": 3,
  "expansionFailed": 0,
  "truncatedTopLevel": 0,
  "items": [
    {
      "type": "top",
      "id": 826405,
      "author": "新米练习菌",
      "authorUserId": "3194882",
      "content": "E大新年快乐~\n承蒙用图\n*^_^*\n以元旦为始，今年也要继续加油！\n  ​",
      "images": [],
      "createdAt": "2026-01-01T20:33:39",
      "ipLocation": "上海市",
      "likeNum": 305
    },
    {
      "type": "reply",
      "id": 836797,
      "author": "新米练习菌",
      "authorUserId": "3194882",
      "content": "有啊，S里的文体娱乐就它",
      "images": [],
      "createdAt": "2026-01-03T08:11:38",
      "ipLocation": "上海市",
      "likeNum": 0,
      "parent": {
        "id": 834331,
        "userName": "同路人_JPQoDg",
        "content": "为什么没有汇添富文体娱乐混合A？",
        "images": [],
        "createdAt": "2026-01-02T15:28:58",
        "ipLocation": "云南省",
        "likeNum": 0
      },
      "replyTo": null
    },
    {
      "type": "reply",
      "id": 847591,
      "author": "新米练习菌",
      "authorUserId": "3194882",
      "content": "还有1份是S的，150目前没有",
      "images": [],
      "createdAt": "2026-01-05T09:46:07",
      "ipLocation": "上海市",
      "likeNum": 0,
      "parent": {
        "id": 826405,
        "userName": "新米练习菌",
        "content": "E大新年快乐~\n承蒙用图\n*^_^*\n以元旦为始，今年也要继续加油！\n  ​",
        "images": [],
        "createdAt": "2026-01-01T20:33:39",
        "ipLocation": "上海市",
        "likeNum": 305
      },
      "replyTo": {
        "id": 847471,
        "userName": "张大帅",
        "content": "纳指100不是还有一份吗？怎么图上显示的是清仓",
        "images": []
      }
    }
  ]
}