{
  "postId": "61735",
  "fetchedAt": "2026-05-09T15:32:05+08:00",
  "totalCommentNum": 230,
  "totalScanned": 175,
  "expandedTopLevel": 3,
  "expansionFailed": 0,
  "truncatedTopLevel": 0,
  "items": [
    {
      "type": "top",
      "id": 991735,
      "author": "新米练习菌",
      "authorUserId": "3194882",
      "content": "中证军工（399967）今天：16868点\n点位已超过2021年的15154，继续创十年新高\n（110倍了？上次1/7 说看烟花时，102倍，已经超过2007年的市梦率的意思吗？）\n【1】2007年\n中证军工，上上波，市梦率在110倍左右（看老大以前发过的《行业指数PE图》大体瞄来的数字）\n最大回撤 -77%\n从2008年01月08日，8278，跌至2008年11月04日，1916\n【2】2015年\n中证军工，上波，市梦率最高在220倍左右\n（超出图的范围了，from 【20251225】（11:04）中证军工指数估值88倍了，88看起来很高，实际上确实很高。但与2015年5月的220倍，那就还是弟弟了。）\n最大回撤-72%\n从2015年06月03日，22063，跌至2018年10月19日，6143\n（记得一起看烟花，想和老大一起看大烟花，我跟车晚，22年才来，只和老大一起看过大雪，乱纪元三颗飞星的极端天气的暴风雪）\n（1/7QM）ETF拯救世界 作者：\n102倍估值的军工。我在这里放个话：这个品种一定会放大烟花，有一天一定是血肉横飞。当然，在这之前能疯狂到哪里我不知道。咱们一起看。\n",
      "images": [],
      "createdAt": "2026-01-12T16:22:00",
      "ipLocation": "上海市",
      "likeNum": 102
    }
  ]
}