{
  "postId": "62563",
  "fetchedAt": "2026-05-09T15:15:06+08:00",
  "totalCommentNum": 409,
  "totalScanned": 369,
  "expandedTopLevel": 4,
  "expansionFailed": 0,
  "truncatedTopLevel": 0,
  "items": [
    {
      "type": "top",
      "id": 1115269,
      "author": "新米练习菌",
      "authorUserId": "3194882",
      "content": "【留言1】WB 25.9.26\n2022年10月10日，我在4400点致敬全指信息。就意味着我知道什么时候，也敢买现在火热的小登股。\n\n今年2月21，7000点附近，清仓了最后一笔信息致敬。\n\n那天到现在，小登们又狂飙了30%。\n\n我后悔吗？少赚了不少。\n\n你觉得呢。\n\n我只赚我能理解的钱。4400致敬也是，7000点清仓也是。事后证明，4400只是阶段最低，后面到过3000多。7000点清仓也不是最高。\n\n我会后悔没有3000多买入，会后悔没有一直拿到现在吗？挺可笑的问题是吧。如果这么想，就是不了解我。\n\n我可以99%的肯定，未来信息为代表的科技aka小登股，会埋掉很多很多很多人。又是很多年赔钱，下一次回本可能又是5年10年后，也许一辈子回不了本。\n\n但我不知道什么时候发生。因为上涨是无限的。人的疯狂，尤其是散户的疯狂是无限的。\n\n但我只吃我能理解的部分。就这么简单。我不理解的钱，跟我无关。\n\n二级市场捡辣鸡冠军: 下一轮信息致敬我还能吃到。收益率不会比持有到现在差，同时安全一万倍\n",
      "images": [],
      "createdAt": "2026-01-16T14:28:48",
      "ipLocation": "上海市",
      "likeNum": 127
    },
    {
      "type": "top",
      "id": 1115377,
      "author": "ETF拯救世界",
      "authorUserId": "793413",
      "content": "70倍估值，怎么玩，我真不知道啊！",
      "images": [],
      "createdAt": "2026-01-16T14:29:44",
      "ipLocation": "北京市",
      "likeNum": 294
    },
    {
      "type": "reply",
      "id": 1115707,
      "author": "新米练习菌",
      "authorUserId": "3194882",
      "content": "【留言2】全指信息-致敬\n致敬金额\t499,552\n收益金额\t219,204\n收回现金\t718,657\n累计收益率\t43.88%\n持有2年多，年化约16.59%\n明细交易过程：\n信息\t买入\t2022-10-10\t0.466\t1072000\t499552\t（已复权）买入100%仓位\t\n信息\t卖出\t2023-03-23\t0.620\t-319000\t-197780\t卖出30%仓位\t\n信息\t卖出\t2024-11-13\t0.678\t-536000\t-363408\t卖出50%仓位\t\n信息\t卖出\t2025-02-21\t0.726\t-216900\t-157469\t（清仓）卖出20%仓位\n",
      "images": [],
      "createdAt": "2026-01-16T14:33:45",
      "ipLocation": "上海市",
      "likeNum": 91,
      "parent": {
        "id": 1115269,
        "userName": "新米练习菌",
        "content": "【留言1】WB 25.9.26\n2022年10月10日，我在4400点致敬全指信息。就意味着我知道什么时候，也敢买现在火热的小登股。\n\n今年2月21，7000点附近，清仓了最后一笔信息致敬。\n\n那天到现在，小登们又狂飙了30%。\n\n我后悔吗？少赚了不少。\n\n你觉得呢。\n\n我只赚我能理解的钱。4400致敬也是，7000点清仓也是。事后证明，4400只是阶段最低，后面到过3000多。7000点清仓也不是最高。\n\n我会后悔没有3000多买入，会后悔没有一直拿到现在吗？挺可笑的问题是吧。如果这么想，就是不了解我。\n\n我可以99%的肯定，未来信息为代表的科技aka小登股，会埋掉很多很多很多人。又是很多年赔钱，下一次回本可能又是5年10年后，也许一辈子回不了本。\n\n但我不知道什么时候发生。因为上涨是无限的。人的疯狂，尤其是散户的疯狂是无限的。\n\n但我只吃我能理解的部分。就这么简单。我不理解的钱，跟我无关。\n\n二级市场捡辣鸡冠军: 下一轮信息致敬我还能吃到。收益率不会比持有到现在差，同时安全一万倍\n",
        "images": [],
        "createdAt": "2026-01-16T14:28:48",
        "ipLocation": "上海市",
        "likeNum": 127
      },
      "replyTo": null
    }
  ]
}