{
  "postId": "67555",
  "fetchedAt": "2026-05-09T14:24:55+08:00",
  "totalCommentNum": 367,
  "totalScanned": 324,
  "expandedTopLevel": 3,
  "expansionFailed": 0,
  "truncatedTopLevel": 0,
  "items": [
    {
      "type": "top",
      "id": 1450909,
      "author": "新米练习菌",
      "authorUserId": "3194882",
      "content": "谢谢老大的「提示词」，太有用了！！！\n我存下来了，以后我也直接帖这段，让AI帮我转文字。\n我也是，非常不喜欢几段文字就能写完的内容却用几分钟的视频表达，阅读速度快的人，觉得非常浪费时间。\n宁可用5分钟读高质量文字，也不花30分钟看/听低密度视频。\n——\n我个人还有个习惯：\n① 如果是视频，知识类，会倍速，一般1.5，1.75，甚至2倍，大部分视频都带着字幕，直接看文字。\n② 如果是直播类，不能倍速，就开启「录制会议」，自己不现场看的，等结束了，让AI当会议整理会议纪要，看一遍文字。\n③ 如果是音频，直接转文字了，然后边听边阅读。\n——\n然后，感慨一下，真的特别喜欢老大是喜欢写文字的人物，我其实并不喜欢播客、直播，觉得太慢了，喜欢文字，同样的时间，可以获得更多，文字也方便收录、存档和整理。\n",
      "images": [],
      "createdAt": "2026-02-20T16:35:09",
      "ipLocation": "上海市",
      "likeNum": 76
    },
    {
      "type": "reply",
      "id": 1450975,
      "author": "ETF拯救世界",
      "authorUserId": "793413",
      "content": "网址附在文字后面即可。",
      "images": [],
      "createdAt": "2026-02-20T16:39:28",
      "ipLocation": "北京市",
      "likeNum": 207,
      "parent": {
        "id": 1450813,
        "userName": "同路人_aTGLOj",
        "content": "怎么输入视频啊？把视频下载到相册里吗？",
        "images": [],
        "createdAt": "2026-02-20T16:30:47",
        "ipLocation": "广东省",
        "likeNum": 11
      },
      "replyTo": null
    },
    {
      "type": "reply",
      "id": 1451617,
      "author": "新米练习菌",
      "authorUserId": "3194882",
      "content": "老大，请允许我再感慨一下，今天收获真大，您那段「提示词」我来回看了好几遍，好精准哦，一边看一边拆解为什么？\n【1】一上来就定身份\n「无损信息转换器」\n（给AI定义了角色，既要不能少信息，也不能添油加醋，不要偷懒，也不要多事）\n【2】要求极其明确，没有模糊词\n- 保留所有逻辑链条\n​- 保留所有具体数据\n​- 保留所有工具或资源名称\n这三句，字字都是干货。\n【3】直接规定输出格式\n二级标题 + 多级列表\n（这是效率控才会写的细节）\n- 标题 = 结构清晰\n​- 列表 = 方便速读\n【4】最后直接定标准\n「确保我读这份总结的获得感不低于看原视频。」\n【5】基础知识/原理铺垫\n对于不熟悉的领域，先打个底。减少阅读陌生抵触感。\n——\n原来指令要这么表达，精准、干净、有力、严谨、不废话，不模糊，有要求，有格式，有标准。\n哇，怎么能写得这么到位啊~\n很有启发，很有帮助，不仅在学习中，也在工作中。\n刚才用了一个“想看又不那么想看”的视频尝试了一下，AI帮我“先看了一遍的视频”回出来的文字描述很清楚。\n真的学到了，谢谢~",
      "images": [],
      "createdAt": "2026-02-20T18:04:02",
      "ipLocation": "上海市",
      "likeNum": 88,
      "parent": {
        "id": 1450909,
        "userName": "新米练习菌",
        "content": "谢谢老大的「提示词」，太有用了！！！\n我存下来了，以后我也直接帖这段，让AI帮我转文字。\n我也是，非常不喜欢几段文字就能写完的内容却用几分钟的视频表达，阅读速度快的人，觉得非常浪费时间。\n宁可用5分钟读高质量文字，也不花30分钟看/听低密度视频。\n——\n我个人还有个习惯：\n① 如果是视频，知识类，会倍速，一般1.5，1.75，甚至2倍，大部分视频都带着字幕，直接看文字。\n② 如果是直播类，不能倍速，就开启「录制会议」，自己不现场看的，等结束了，让AI当会议整理会议纪要，看一遍文字。\n③ 如果是音频，直接转文字了，然后边听边阅读。\n——\n然后，感慨一下，真的特别喜欢老大是喜欢写文字的人物，我其实并不喜欢播客、直播，觉得太慢了，喜欢文字，同样的时间，可以获得更多，文字也方便收录、存档和整理。\n",
        "images": [],
        "createdAt": "2026-02-20T16:35:09",
        "ipLocation": "上海市",
        "likeNum": 76
      },
      "replyTo": null
    }
  ]
}