{
  "id": "69247",
  "url": "https://qieman.com/content/content-detail?postId=69247",
  "richContent": "<p>我再说一次，今年开始的一些操作，一定会让一部分朋友中短期比以前更加难受。</p>\n<p></p>\n<p>因为我不会顾虑太多你中短期的持仓感受了。</p>\n<p></p>\n<p>但是长期看，是对所有朋友的更加负责。</p>\n<p></p>\n<p>如果之前已经经常很难受，那么真的建议你不要再参考我的投资。因为你以后只会更加难受。因为我会买入更多下跌的品种。</p>\n<p></p>\n<p>再说一次，只要你觉得难受，不舒服，请停止参考我的投资。</p>\n<p></p>\n<p>因为你以后只会更加不舒服。</p>\n<p></p>\n<p>勿谓言之不预。</p>",
  "images": [],
  "audioUrl": "",
  "audioDuration": 0,
  "retweetContent": "",
  "retweetAuthor": ""
}