{
  "id": "72553",
  "url": "https://qieman.com/content/content-detail?postId=72553",
  "richContent": "<p>几乎没有投资价值但是有交易价值的具象化。</p>\n<p></p>\n<p>整个市场绝大多数股票都是如此。</p>\n<p></p>\n<p>低买高卖有收益，追高血本无归。</p>\n<p></p>\n<p>非常艰难的市场。</p>\n<p></p>\n<p></p>\n<p></p>\n<img src=\"https://cdn-community.qieman.com/6F4DF025-2EBB-48E4-A706-5EA7630C7409.png\" />\n<img src=\"https://cdn-community.qieman.com/F8CED1D4-32E2-45D0-BA37-84C39F90847C.png\" />\n<img src=\"https://cdn-community.qieman.com/D38CB2DE-E1CC-4344-A212-1B2B8C17DE85.png\" />",
  "images": [],
  "audioUrl": "",
  "audioDuration": 0,
  "retweetContent": "",
  "retweetAuthor": ""
}