{
  "id": "wb_4455150783833644",
  "url": "https://weibo.com/5687069307/In8ISg5iY",
  "richContent": "<p>今年之前，新年红包都是微博和公众号随机发。几千位朋友都能拿到。</p>\n<p>今年初，我突然发现，不止是只有朋友关注我，还有辣鸡盯着我的微博天天挑毛病随时准备开喷。</p>\n<p>让这些辣鸡抢到一分钱我都会觉得恶心，所以今年开始，由阳光普照，改成发给真朋友。</p>\n<p>然而怎么知道这么多人里面谁是真朋友很难。我也只能尽量想办法。</p>\n<p>今年微博送礼物规则是这样。</p>\n<p>过去三个月，互动总分前十名的朋友可以获得礼物。</p>\n<p>大奖依然是按照明天上证指数收盘最后一位数字定。十位朋友会按照分数有个排名，谁的排名与最后一位相同谁获大奖。剩下的九位朋友按分数从高到低获得其它奖。</p>\n<p>奖品是：</p>\n<p>大奖 京东购物卡 880</p>\n<p>第二名 京东购物卡 500</p>\n<p>第三名 京东购物卡 300</p>\n<p>第四到十名 京东购物卡 200</p>\n<p>本来想买礼物给大家，后来想还是各位喜欢什么自己买吧。</p>\n<p>钱不多，主要是因为我穷。没有赞助商，都是自己掏腰包。拿到的别嫌少，没拿到的别生气，公众号还会发。公众号也没拿到也别生气，快过年了，开开心心的啊。</p>\n<p>这是三个月的互动数据，之后会有个综合排名，明天与结果一起公布。榜上的朋友也可以自己算算，看会不会与我算的有差别。</p>",
  "images": [
    "006cSmwjly1gaek2q32syj30u03b61bp",
    "006cSmwjly1gaek2qgco1j30u038gtre",
    "006cSmwjly1gaek2qyzaaj30u03kcttn"
  ],
  "audioUrl": "",
  "audioDuration": 0,
  "retweetContent": "",
  "retweetAuthor": ""
}