{
  "id": "wb_4365683234203625",
  "url": "https://weibo.com/5687069307/HryIHhDyp",
  "richContent": "<p>最后一次说这件事，以后也不说了。省得有人说我带节奏（奇怪了自己的微博谈谈自己的想法带什么节奏……）</p>\n<p>第一，坚决反对婚内出轨。</p>\n<p>我不是说婚内出轨的都是人渣，因为出轨有可能很多原因，一个家庭的情况外人咱们也弄不清楚。但是只要出轨，同时对另一半造成伤害的，都是不道德的。受到再大的精神以及财务惩罚也应该。出轨不违法不犯罪，但要做好承受一切后果的准备。</p>\n<p>第二，事情的真相非常重要。</p>\n<p>其实很多事情的真相我们永远也不会知道。但我内心深处还是希望能够了解。这个世界太多虚假的东西，虽然我们也许永远也无法触及真相，但我希望可以努力更加接近。</p>\n<p>我痛恨为了自己的利益造谣生事，无中生有，颠倒黑白。这种人我非常痛恨，非常。这些人知道真相，但极力扭曲，可以说是垃圾中的战斗机。</p>\n<p>我也会对一些朋友遇到事情感性大于理性，无关利益但缺少理性的行为感到遗憾。但我一定程度上很理解。很多事情我们都是立场决定思维，所以我理解。也许真相对这些朋友来说不重要，但我觉得遇到事情，理性多一点比较好。</p>\n<p>理性是什么？理性就是出轨背叛要谴责，是不是强奸是另一回事。不能把事情混起来谈。是不是强奸，要看证据链，而不是脑子一热只听一面之词，因为某种原因感性战胜理性。不能认为某类人就一定是弱者，不能贴标签。真的，别贴标签。就事论事。</p>\n<p>如果是强奸，该关就关，该毙就毙。如果不是，就不能因为讨厌一个人而诬陷栽赃。</p>\n<p>第三，坚决支持男女平权。</p>\n<p>性别歧视的男人都是人渣。女性是这个地球上最可爱的生物（说可爱会不会有歧视的味道？如果有，我删掉……），不接受反驳！（怎么还有人认为我不支持不喜欢不认同女性呜呜呜冤枉死我了……）</p>",
  "images": [],
  "audioUrl": "",
  "audioDuration": 0,
  "retweetContent": "",
  "retweetAuthor": ""
}