{
  "id": "wb_4260548394235394",
  "url": "https://weibo.com/5687069307/Gpp8HhLOO",
  "richContent": "<p>我理解的“趋势”，与很多人不同。好多人一天两天，就能看出趋势变了。</p>\n<p>我不行，我能力比较差。在我的观察体系中，可能甚至需要数周，才能判断大概率趋势变了还是没变。</p>\n<p>确实，我没有那些灵敏度高的人抓到超级大底的可能性大。但是，我的概率会比较大。而且我很难被骗。你拉两根阳线想骗我，呵呵哒。</p>\n<p>跌三年，你可以猜400多个底。我可能只判断一次。</p>\n<p>判断世间大势其实很难。太早不行。比如你和6个小伙伴去找个游船商量要做点大事，我看没几个人敢加入你们。虽然也许你们其中一个人最后会特别NB。</p>\n<p>太晚也不行。都打到海南岛了你再举手投降没什么用，十几年后还要被干。</p>\n<p>所以，你怎么才能在趋势转折的时候，顺势而为，是一个非常考验眼光的事。太早太晚都不行。</p>\n<p>很多人每天猜底，我的意见是最好休息休息。伤了钱包厚度是小事，给自己整的每天都很焦虑没有意义。</p>\n<p>站高一点，看远一点。不要在意每天的这点波动。</p>\n<p>多大点事儿啊，踏踏实实的。</p>",
  "images": [],
  "audioUrl": "",
  "audioDuration": 0,
  "retweetContent": "",
  "retweetAuthor": ""
}