{
  "id": "wb_4949806419809107",
  "url": "https://weibo.com/7519797263/NkTGVF9Np",
  "richContent": "<p>技术探讨①</p>\n<p>在我的技术体系中，压力和支撑分别来自于几个角度。其中一个角度是“均线”。</p>\n<p>简单理解，均线就是过去某段时间内大家的成本平均值连成的线。</p>\n<p>比如5日均线就是过去5天买入人的平均成本。250日就是过去一年买入人的平均成本。</p>\n<p>一般来说，我会把一些中期、长期的均线定为自己的观察指标。</p>\n<p>那么问题来了，你认为从原理上讲，为什么均线，也就是某段时间买入人的平均成本是一个压力或者支撑？</p>\n<p>从交易者的心理层面讲，为什么均线很多时候能起到作用？</p>\n<p>提示：</p>\n<p>我是从两个心理层面角度去理解均线为什么起作用的。</p>",
  "images": [],
  "audioUrl": "",
  "audioDuration": 0,
  "retweetContent": "",
  "retweetAuthor": ""
}