{
  "id": "wb_4675957380878661",
  "url": "https://weibo.com/5687069307/KvRZU3GzX",
  "richContent": "<p>目前市场有非常有意思的现象，需要各位留心观察并记录，我相信，对你我未来几十年的投资生涯有很大帮助：</p>\n<p>目前市场有些行业，由于各方面的压力，当然最主要是ZC方面的压力，导致行业估值比较低。当然没到最低。</p>\n<p>这个时候，我会观察，到底是“便宜”最终会赢，还是“跌幅巨大后的新利空”会赢。</p>\n<p>在我以往的观察中，绝大多数情况是便宜会赢。跌幅巨大后的利空通常会砸出一个结结实实的钻石坑。在这种时候，会有无数人告诉你：</p>\n<p>这次不一样；这个公司/行业彻底完了……</p>\n<p>我不能确定这次是否还像以前一样，但我选择经验主义，也就是说，我愿意用一点筹码赌一赌便宜更重要。</p>\n<p>目前来看，被打压的比较凶的是医药、传媒、中概互联网。</p>\n<p>这三个行业，互联网最近几个月开始买，传媒最近一个月在买，医药前一波减持后还没开始买回，但最终会买。</p>\n<p>便宜还是暴跌后的利空，谁会胜利？</p>\n<p>几年后，这将是一条值得回味的微博。javascript:void(0)</p>",
  "images": [],
  "audioUrl": "",
  "audioDuration": 0,
  "retweetContent": "",
  "retweetAuthor": ""
}