{
  "id": "wb_4476572046280967",
  "url": "https://weibo.com/5687069307/Iw7ZiqlXV",
  "richContent": "<p>红利基金的分红时点也很有意思。拿富国红利来说，2008年成立，至今12年，分红8次。</p>\n<p>分别是2010年0.245；2011年0.13；2012年0.026；2015年0.056；2016年0.35；2017年0.3；2018年0.188；2020年0.11</p>\n<p>都是年初分红。记住，都是这些年度的年初。这个很重要。</p>\n<p>你会发现，2009年、2013年、2014年、2019年初，没有分。而这四年，竟然与我们定义的钻石坑神一样的重合了。</p>\n<p>2008年底钻石坑、2012年底钻石坑、2018年底钻石坑。</p>\n<p>也就是说，在钻石坑中，连红利基金都赔的没钱分红了。所以，红利基金没钱分红，是你判断钻石坑的又一个依据。</p>\n<p>另外，分红越多，恐怕越应该警惕，你观察一下。</p>",
  "images": [],
  "audioUrl": "",
  "audioDuration": 0,
  "retweetContent": "",
  "retweetAuthor": ""
}