{
  "id": "wb_4596866266437377",
  "url": "https://weibo.com/5687069307/JEDVUr0EF",
  "richContent": "<p>说起指导孩子打理钱这件事，我简直是满身屠龙之技却无处施展。为什么，</p>\n<p>因为即将8岁的他对钱毫无兴趣。</p>\n<p>喷了。我像他这么大的时候，多么渴望兜里钱多点能买好吃的好玩的东西啊……</p>\n<p>前几天我决定主动引导他发现钱的好处：</p>\n<p>比如，“你是不是想吃冰激淋啊，我不给你买，如果你有钱就可以自己买啊。”“你是不是想再买一个奥特曼或者乐高啊，如果你有钱了，想买哪个都可以啊，爸爸妈妈都没有权利干涉你。”</p>\n<p>终于，他有点明白钱的好处了。</p>\n<p>我开心的帮他制定了“基础零花钱+业绩提成零花钱”的收入路线，“任何收入拿出30%投资，30年后就不用为了钱工作”的理财路线，“随便买自己最喜欢最想买的好东西并教会他使用微信支付”的支出路线……</p>\n<p>屠龙之战终于开场了……老父亲泪流满面。</p>",
  "images": [],
  "audioUrl": "",
  "audioDuration": 0,
  "retweetContent": "",
  "retweetAuthor": ""
}