{
  "id": "wb_4858120675268971",
  "url": "https://weibo.com/7519797263/MonZ1m6Hp",
  "richContent": "<p>接上文。</p>\n<p>2021年江西大致处于人均GDP省份排名居中的位置，6.55万元，相当于1万美元左右。</p>\n<p>按照世界人口超过2000万的大国和地区的情况看，我个人认为，当江西的人均GDP达到2万美元左右，也就是大致波兰、沙特的世界排名50名附近，生活应该就会比较舒服了。</p>\n<p>当江西GDP超过3万美元，相当于西班牙、中国台湾、韩国，那应该是比较富裕了。</p>\n<p>当江西GDP超过4万美元，相当于日本、法国，就已经进入发达国家状态。</p>\n<p>当江西GDP超过5万美元，就到了中国香港、德国、加拿大的状态。</p>\n<p>超过7万美元，就是美国的状态。</p>\n<p>北京、上海、深圳人均GDP高，不能代表中国老百姓的日子有多富。大家都富起来才行。</p>\n<p>踏踏实实发展经济吧，大家的日子都越来越好，不折腾。</p>",
  "images": [],
  "audioUrl": "",
  "audioDuration": 0,
  "retweetContent": "",
  "retweetAuthor": ""
}