{
  "id": "wb_4342092891288555",
  "url": "https://weibo.com/5687069307/HhF1L5pd9",
  "richContent": "<p>昨天在且慢问答回答了一个关于“突然有大笔可投资资金如何补车”的问题。</p>\n<p>我觉得微博也有很多朋友有这个情况。</p>\n<p>那篇文章很长，我简单总结成一句话吧。</p>\n<p>如果你有年终奖/压岁钱/之前犹豫后来坚定信心想加大投入：</p>\n<p>在150亏损的情况下，调高每份金额，根据补仓提醒全部补足低于我成本的。</p>\n<p>在150份盈利的情况下，将资金分成若干份。分多少份看这个资金的性质。比如是按年发的年终奖，那么就除以15或者16，然后每个月一份参考S。</p>\n<p>参考S的时候如果150份又亏损了，则把剩余的放入150补仓。</p>\n<p>问题的关键是，你150盈利的时候，不要大笔加仓。否则计划设计的再好，也很难让你有满意的收益。</p>\n<p>这就像你1000点买了1万块，6000点心情激动加了10万一样。</p>",
  "images": [],
  "audioUrl": "",
  "audioDuration": 0,
  "retweetContent": "",
  "retweetAuthor": ""
}