{
  "id": "wb_4479062204640190",
  "url": "https://weibo.com/5687069307/IxaLGjt7M",
  "richContent": "<p>有两种问题不要再私信我了。</p>\n<p>第一种是：</p>\n<p>基金怎么买，买什么基金，什么叫etf。</p>\n<p>我没有兴趣，没有精力，没有动力去做基金普及的工作。看我的东西，有一定金融知识基础，最好有几年交易经验的是最合适的。如果你没有，也不是不能看，前提是你先百度一下基础知识再来。</p>\n<p>否则，取关我是最好的。我其实没什么好关注的，能力一般，聊天乏味，智商不在线。</p>\n<p>第二种是：</p>\n<p>我买了xx基金，xx股票，被套了，怎么办。</p>\n<p>我说过无数次了。你买的东西涨了或者跌了怎么办，是交易前应该想好并设计应对方案的。不是交易后再去想，那就晚了。所以你问我，我更不知道。因为我不知道你的财务状况个人情况，更因为我不是什么帮你看股票看基金的老师，别问我。</p>",
  "images": [
    "006cSmwjly1gciuc56zxxj30ce02kt8n"
  ],
  "audioUrl": "",
  "audioDuration": 0,
  "retweetContent": "",
  "retweetAuthor": ""
}