{
  "id": "wb_4739741767439399",
  "url": "https://weibo.com/5687069307/LgFRCvdkj",
  "richContent": "<p>在我看来，资产管理行业应该是双向选择。这件事我已经阐述过了。</p>\n<p>可惜，99.99999%的资管都是张开双臂欢迎所有资金。因为资管行业追求的是规模。规模大了，对于管理人来说，才有更好的回报。</p>\n<p>不好意思，我就是那0.00001%其中的一个。</p>\n<p>我的钱不多，但踏踏实实过一辈子应该够了。我也不想再买什么豪宅，也不想买什么豪车。</p>\n<p>吃喝嫖赌毒。一个正常人，敞开了吃，能吃多少？喝，不好意思，除了心情好的时候喝点自己调的鸡尾酒，或者极其偶尔与朋友小酌两杯，平常滴酒不沾。喜欢美女，但弱水三千只取一瓢饮足以，所以也没有更多的花销。赌的乐趣怎么比得上在股市搏杀？毒更不用说。</p>\n<p>所以，还是那句话，我很喜欢钱，但目前阶段我的需求真的不大。多点更好，少了也没有大的所谓。</p>\n<p>更何况，我的计划是完全公开。你到别的地方跟车，我也毫无收益。就凭这一点，你就应该知道做这件事，对我最重要的绝对不是钱。</p>\n<p>从十几年前开始的第一轮，第二轮，全都是公开的，跟钱有关？</p>\n<p>那么是什么？</p>\n<p>我总说，做投资要不忘初心。我想，做每件事都应该不忘初心。</p>\n<p>我做这件事的初心，就是想证明在A股这样的市场上，只要你理性，就一定能挣钱。然后对我最重要的事情，就是我不希望任何一个人因为我的分享而赔钱。</p>\n<p>好了，第三轮至今，只要是前几年开始跟车的朋友，93%都是赚钱的。所有持仓品种，绝大多数也都是赚钱的，只有几个新建仓的品种是浮亏的。</p>\n<p>93%的人赚钱，这在A股市场上难道不是一个奇迹吗。这样奇迹的背后，是严格控制成本的制度设计，也是各位即使在最黑暗的时候也不放弃，也坚信的结果。</p>\n<p>这一两年，我为什么跪求新朋友不要跟？因为我知道你现在买很难马上赚钱。而新人的特点就是什么都不懂，他们根本就不知道我们的节奏是怎么控制的，根本就不懂买的那一点点仓位即使上涨也赚不到大钱。又因为没有以前低成本品种的对冲，导致整体浮亏。</p>\n<p>这一切我早已预见到。所以我一直说新朋友不要跟。我不是ZK，也不是GL。我不需要规模，我只想要一件事：</p>\n<p>那就是你赚钱！</p>\n<p>这对我来说最重要。</p>\n<p>有些人，根本就没有做好准备。说浮亏的那些，我问你，你这两年开始买，你的150份，买了有15份吗？买了有20份吗？你连10%仓位都没买好，你着什么急赚钱？</p>\n<p>我告诉你，你这样的，就是我选择让你出去的那种。你选择了我，我很感激你的信任。但我不选择你。</p>\n<p>对我来说，规模也好，跟车的人也好有多少，不能说一点不重要，但绝对不是最重要的。</p>\n<p>最重要的，是我希望与理性的人们一起，一起赚到钱。</p>\n<p>没有比这个更重要的！</p>",
  "images": [],
  "audioUrl": "",
  "audioDuration": 0,
  "retweetContent": "",
  "retweetAuthor": ""
}