{
  "id": "wb_4570067646550735",
  "url": "https://weibo.com/5687069307/JtoMkru91",
  "richContent": "<p>投资其实一定程度上是一个人价值观的折射。</p>\n<p>我特别讨厌那种谁涨的好就吹谁买谁，谁一个阶段表现不好就把它踩在脚下乱喷的人。（这几年我相信你也见过不少这样的人）</p>\n<p>你如果是机构，需要业绩排名，要恰饭，我能理解。你一个个人投资者天天嫌贫爱富，就只能说明你这个人的品质有问题。</p>\n<p>这个说的并不严重。总体而言，就是你并没有什么信仰，你只是单纯的喜欢钱而已。</p>\n<p>然而，事实是，没有信仰，你还真挣不到，守不住大钱。</p>\n<p>所以这种人我不喜欢，更不喜欢你出现在我这里。不喜欢你参考我的投资，不喜欢你评论我的微博。</p>\n<p>价值观、世界观差不多的人，才能一起努力完成一件很难完成的事。倒不是说谁对谁错，我只是单纯的讨厌你而已。</p>",
  "images": [],
  "audioUrl": "",
  "audioDuration": 0,
  "retweetContent": "",
  "retweetAuthor": ""
}