{"updatedAt":"2026-05-04T10:27:26Z","plan":"150份计划","poName":"长赢指数投资计划-150份","totalUnit":150,"return_method":"avg_compound (geometric mean of FIFO trip returns)","framework":{"philosophy":[{"id":"low_buy_high_sell","title":"低买高卖","desc":"宽基的本质是周期性的癫狂和绝望，靠波动赚钱。"},{"id":"left_side","title":"左侧交易","desc":"越涨越卖、越跌越买。不猜顶底，分批进出。"},{"id":"time_space","title":"时间+空间维度","desc":"下跌幅度触发（空间）或月度节奏触发（时间），至少占其一。"},{"id":"discipline","title":"机械执行","desc":"做'野生AI'，纪律高于判断，无视外界声音。"},{"id":"diversify","title":"风格分散","desc":"价值/成长/红利都要有，无论哪个风格涨都赚钱。"},{"id":"rotation","title":"做'好人'轮动","desc":"卖热门给抢的人，买冷门为他们分担。卖热买冷。"},{"id":"rebalance","title":"动态再平衡","desc":"仓位超合理区间则减，市场连涨3月+则减。"},{"id":"grid_profit","title":"网格留利润","desc":"波动大的不死品种适合网格，每格留利润给下一轮。"}],"categories":{"broad_index":{"label":"宽基指数","examples":["沪深300","中证500","上证50","中证800","中证1000","创业板","A500"],"approach":"低买高卖波段，不长期持有","rationale":"A股新股大量上市，宽基本质是'周期性的癫狂和绝望'。护城河巨头占比少，靠周期波动赚钱。低买高卖一定不会错。","fund_name_keywords":["300","500","50ETF","180ETF","全指","指数增强","A500","1000","创业板"]},"dividend":{"label":"红利/低波","examples":["中证红利","红利低波100","300红利"],"approach":"长期持有为主，下跌加仓，少量轮换","rationale":"A股市场特殊，红利能稳定分红，跌了买更多反而拿到更多分红。2017-2018第一波建仓，目前开启第二轮。S计划改为每月持续买入。","fund_name_keywords":["红利"]},"sector":{"label":"行业指数","examples":["医药","消费","传媒","环保","证券","金融地产","军工","新能源"],"approach":"波段为主，估值低位建仓","rationale":"行业指数有交易价值无投资价值，靠周期性波动。大幅下跌后开始波段，做低成本，等估值修复或下一轮风口。","fund_name_keywords":["医药","医疗","健康","消费","传媒","环保","证券","金融","地产","军工","新能源"]},"bond":{"label":"债券/固收","examples":["国开债","信用债","美元债","纯债"],"approach":"防守仓位，再平衡工具","rationale":"提款计划留3年现金类资产应对熊市；用于股债再平衡。","fund_name_keywords":["国开债","信用债","纯债","美元债","短债","1-3年","7-10年"]},"overseas":{"label":"海外/QDII","examples":["恒生","标普500","纳指","中概互联","海外医疗","全球油气"],"approach":"分散配置，部分波段","rationale":"海外配置降低单一市场风险，叠加汇率维度。","fund_name_keywords":["恒生","标普","海外","美元","全球","QDII","中概","纳斯达克","原油","油气","黄金"]},"convertible":{"label":"可转债/混合","examples":["可转债"],"approach":"弱相关防御","rationale":"可转债有股性也有债性，是相对独立的资产。","fund_name_keywords":["可转债"]}},"sell_rules":[{"id":"SELL_RETURN_60","name":"收益率≥60% 加大减仓","category":"broad_index","description":"宽基平均收益率达到 60%+，进入持续减仓阶段，每周/每月稳定卖出。","source":"21493 (2026-01-07): 把平均收益率60%以上的中证500分一些给别人"},{"id":"SELL_RETURN_30","name":"收益率≥30% 启动减仓","category":"broad_index","description":"宽基收益率超过 30% 开始考虑首次减仓 1 份，标志性减仓节点。","source":"历史交易模式 (2021-09 中证500首卖 +37.4%, 2025-08 +30.4%)"},{"id":"SELL_RESISTANCE","name":"技术压力位减仓","category":"any","description":"碰到小压力位继续缓慢减持，到大压力位进行更大笔减持。","source":"21547 (2026-01-09): 500碰到小压力位，继续缓慢减持"},{"id":"SELL_REBALANCE_RALLY","name":"大盘连涨再平衡","category":"any","description":"大盘连涨 3 个月以上，持仓仓位超出合理区间，动态再平衡减仓。","source":"2904 (2023-02-01): 大盘连涨3个月，仓位超合理区间"},{"id":"SELL_VALUATION_PEAK","name":"估值历史高位","category":"any","description":"估值进入历史高位区间（如军工100倍向2007/2015高点挺进），减仓倒计时。","source":"60643 (2026-01-08): 中证军工100倍，减仓倒计时"},{"id":"SELL_GRID_PROFIT","name":"网格波段获利","category":"sector","description":"波动大的不死品种，跌X%买，涨X%卖，每格留利润。","source":"66685 (2026-02-07): 网格波段适合波动巨大的不死品种"},{"id":"SELL_MECHANICAL","name":"机械执行（兜底标签）","category":"any","description":"正常调仓，策略触发卖出机制，不代表看多看空，机械执行。","source":"19297 (2025-08-13): 交易策略触发卖出机制，机械执行"}],"buy_rules":[{"id":"BUY_DIVIDEND_MONTHLY","name":"红利每月持续买入","category":"dividend","description":"S计划红利每月至少买1份，承受短期下跌、坚持纪律持续投入。","source":"73435 (2026-04-15): 估值不低也要继续买入红利"},{"id":"BUY_DIVIDEND_DROP_3","name":"红利下跌3% 加仓","category":"dividend","description":"预设加仓位置在当前价位下跌 3% 左右。","source":"58201 (2025-12-17): 红利100下一次加仓位置约下跌3%"},{"id":"BUY_LEFT_SIDE_GRID","name":"左侧分批买入（空间维度）","category":"any","description":"下跌 5%/7%/10% 加仓，避免筹码聚集在下跌高位。空间策略。","source":"WX-2021-09-27: 我的左侧买入节奏"},{"id":"BUY_LEFT_SIDE_TIME","name":"左侧分批买入（时间维度）","category":"any","description":"按时间节奏定期买入，不一定是定投，但保持时间分散。","source":"WX-2021-09-27: 时间空间至少占其一"},{"id":"BUY_VALUATION_LOW","name":"估值历史低位建仓","category":"sector","description":"行业指数跌至估值历史低位（如医药 PB 2008-10 以来最低），开始建仓。","source":"71383 (2026-03-23): 全指医药估值历史第二低"},{"id":"BUY_ROTATION","name":"轮动 — 卖热买冷","category":"any","description":"把高收益的卖一些，把跌幅大的辣鸡品种买一些回来，做'好人'。","source":"21493 (2026-01-07): 把500分一些给别人，把辣鸡消费买回来"},{"id":"BUY_AFTER_BIG_DROP","name":"腰斩后波段建仓","category":"sector","description":"基金跌幅 50%+ 后开始波段建仓，分批降低成本。","source":"74233 (2026-04-25): 医疗基金跌60%多，腰斩开始买，做波段"}],"hold_rules":[{"id":"HOLD_DIVIDEND_LONG","name":"红利长期持有","category":"dividend","description":"第一轮红利15年只卖2份，剩余可能一直持有。","source":"74371 (2026-04-22): 第一波红利建仓，长期持有"},{"id":"HOLD_BOND_DEFENSE","name":"债券防守仓位","category":"bond","description":"始终保留 3 年提款额的现金类资产，确保熊市不被动卖股。","source":"61459 (2026-01-10): 提款计算器Q&A"}]},"tagged_trades":[{"date":"2016-09-29","fund":"南方原油A","code":"501018","category":"overseas","action":"sell","unit":1,"buy_date":"2016-08-01","buy_adj":0.8667,"sell_adj":0.9543,"return_pct":10.1,"hold_days":59,"tags":[{"rule_id":"SELL_MECHANICAL","rule_name":"机械执行（兜底标签）","confidence":0.3}],"primary_tag":"SELL_MECHANICAL","sell_streak":1},{"date":"2016-12-14","fund":"华夏上证50ETF联接A","code":"001051","category":"broad_index","action":"sell","unit":1,"buy_date":"2015-08-03","buy_adj":0.817,"sell_adj":0.784,"return_pct":-4.0,"hold_days":499,"tags":[{"rule_id":"SELL_MECHANICAL","rule_name":"机械执行（兜底标签）","confidence":0.3}],"primary_tag":"SELL_MECHANICAL","sell_streak":1},{"date":"2017-07-31","fund":"华夏恒生ETF联接A","code":"000071","category":"overseas","action":"sell","unit":1,"buy_date":"2015-08-31","buy_adj":1.047,"sell_adj":1.4411,"return_pct":37.6,"hold_days":700,"tags":[{"rule_id":"SELL_RESISTANCE","rule_name":"技术压力位减仓","confidence":0.6}],"primary_tag":"SELL_RESISTANCE","sell_streak":1},{"date":"2017-11-15","fund":"华夏恒生ETF联接A","code":"000071","category":"overseas","action":"sell","unit":1,"buy_date":"2015-10-08","buy_adj":1.078,"sell_adj":1.5077,"return_pct":39.9,"hold_days":769,"tags":[{"rule_id":"SELL_RESISTANCE","rule_name":"技术压力位减仓","confidence":0.6}],"primary_tag":"SELL_RESISTANCE","sell_streak":2},{"date":"2018-04-26","fund":"广发中债7-10年国开债指数A","code":"003376","category":"bond","action":"sell","unit":1,"buy_date":"2017-02-14","buy_adj":0.9507,"sell_adj":0.9688,"return_pct":1.9,"hold_days":436,"tags":[{"rule_id":"SELL_MECHANICAL","rule_name":"机械执行（兜底标签）","confidence":0.3}],"primary_tag":"SELL_MECHANICAL","sell_streak":1},{"date":"2018-05-31","fund":"华宝标普油气上游股票人民币(LOF)A","code":"162411","category":"overseas","action":"sell","unit":1,"buy_date":"2017-04-19","buy_adj":0.6,"sell_adj":0.667,"return_pct":11.2,"hold_days":407,"tags":[{"rule_id":"SELL_MECHANICAL","rule_name":"机械执行（兜底标签）","confidence":0.3}],"primary_tag":"SELL_MECHANICAL","sell_streak":1},{"date":"2018-07-05","fund":"广发中债7-10年国开债指数A","code":"003376","category":"bond","action":"sell","unit":1,"buy_date":"2017-04-25","buy_adj":0.9456,"sell_adj":0.9937,"return_pct":5.1,"hold_days":436,"tags":[{"rule_id":"SELL_MECHANICAL","rule_name":"机械执行（兜底标签）","confidence":0.3}],"primary_tag":"SELL_MECHANICAL","sell_streak":2},{"date":"2018-08-06","fund":"广发中债7-10年国开债指数A","code":"003376","category":"bond","action":"sell","unit":1,"buy_date":"2017-05-23","buy_adj":0.9354,"sell_adj":1.0019,"return_pct":7.1,"hold_days":440,"tags":[{"rule_id":"SELL_MECHANICAL","rule_name":"机械执行（兜底标签）","confidence":0.3}],"primary_tag":"SELL_MECHANICAL","sell_streak":3},{"date":"2018-08-15","fund":"华夏海外收益债券A","code":"001061","category":"overseas","action":"sell","unit":1,"buy_date":"2017-08-15","buy_adj":1.40914183,"sell_adj":1.43787637,"return_pct":2.0,"hold_days":365,"tags":[{"rule_id":"SELL_MECHANICAL","rule_name":"机械执行（兜底标签）","confidence":0.3}],"primary_tag":"SELL_MECHANICAL","sell_streak":1},{"date":"2018-08-20","fund":"博时信用债纯债债券A","code":"050027","category":"bond","action":"sell","unit":1,"buy_date":"2016-11-30","buy_adj":1.3721,"sell_adj":1.4479,"return_pct":5.5,"hold_days":628,"tags":[{"rule_id":"SELL_MECHANICAL","rule_name":"机械执行（兜底标签）","confidence":0.3}],"primary_tag":"SELL_MECHANICAL","sell_streak":1},{"date":"2018-08-20","fund":"华宝标普油气上游股票人民币(LOF)A","code":"162411","category":"overseas","action":"sell","unit":1,"buy_date":"2017-08-15","buy_adj":0.502,"sell_adj":0.682,"return_pct":35.9,"hold_days":370,"tags":[{"rule_id":"SELL_RESISTANCE","rule_name":"技术压力位减仓","confidence":0.6}],"primary_tag":"SELL_RESISTANCE","sell_streak":2},{"date":"2018-10-30","fund":"华夏海外收益债券A","code":"001061","category":"overseas","action":"sell","unit":1,"buy_date":"2017-09-15","buy_adj":1.3987974,"sell_adj":1.44477266,"return_pct":3.3,"hold_days":410,"tags":[{"rule_id":"SELL_MECHANICAL","rule_name":"机械执行（兜底标签）","confidence":0.3}],"primary_tag":"SELL_MECHANICAL","sell_streak":2},{"date":"2018-10-30","fund":"广发纯债债券A","code":"270048","category":"bond","action":"sell","unit":1,"buy_date":"2017-10-16","buy_adj":1.33,"sell_adj":1.3975,"return_pct":5.1,"hold_days":379,"tags":[{"rule_id":"SELL_MECHANICAL","rule_name":"机械执行（兜底标签）","confidence":0.3}],"primary_tag":"SELL_MECHANICAL","sell_streak":1},{"date":"2018-11-30","fund":"广发中债7-10年国开债指数A","code":"003376","category":"bond","action":"sell","unit":1,"buy_date":"2017-07-31","buy_adj":0.9565,"sell_adj":1.0285,"return_pct":7.5,"hold_days":487,"tags":[{"rule_id":"SELL_MECHANICAL","rule_name":"机械执行（兜底标签）","confidence":0.3}],"primary_tag":"SELL_MECHANICAL","sell_streak":4},{"date":"2019-01-15","fund":"广发中债7-10年国开债指数A","code":"003376","category":"bond","action":"sell","unit":1,"buy_date":"2017-11-15","buy_adj":0.9334,"sell_adj":1.048,"return_pct":12.3,"hold_days":426,"tags":[{"rule_id":"SELL_MECHANICAL","rule_name":"机械执行（兜底标签）","confidence":0.3}],"primary_tag":"SELL_MECHANICAL","sell_streak":5},{"date":"2019-01-15","fund":"华夏海外收益债券A","code":"001061","category":"overseas","action":"sell","unit":1,"buy_date":"2018-01-19","buy_adj":1.40799245,"sell_adj":1.4298307,"return_pct":1.6,"hold_days":361,"tags":[{"rule_id":"SELL_MECHANICAL","rule_name":"机械执行（兜底标签）","confidence":0.3}],"primary_tag":"SELL_MECHANICAL","sell_streak":3},{"date":"2019-03-07","fund":"广发中证500ETF联接C","code":"002903","category":"broad_index","action":"sell","unit":1,"buy_date":"2018-08-06","buy_adj":0.8407,"sell_adj":0.9437,"return_pct":12.2,"hold_days":213,"tags":[{"rule_id":"SELL_MECHANICAL","rule_name":"机械执行（兜底标签）","confidence":0.3}],"primary_tag":"SELL_MECHANICAL","sell_streak":1},{"date":"2019-05-15","fund":"易方达消费行业","code":"110022","category":"sector","action":"sell","unit":1,"buy_date":"2018-10-30","buy_adj":1.713,"sell_adj":2.678,"return_pct":56.3,"hold_days":197,"tags":[{"rule_id":"SELL_RESISTANCE","rule_name":"技术压力位减仓","confidence":0.6}],"primary_tag":"SELL_RESISTANCE","sell_streak":1},{"date":"2019-12-02","fund":"易方达创业板ETF联接A","code":"110026","category":"broad_index","action":"sell","unit":1,"buy_date":"2017-06-30","buy_adj":1.8835,"sell_adj":1.7296,"return_pct":-8.2,"hold_days":885,"tags":[{"rule_id":"SELL_MECHANICAL","rule_name":"机械执行（兜底标签）","confidence":0.3}],"primary_tag":"SELL_MECHANICAL","sell_streak":1},{"date":"2020-02-26","fund":"广发中证500ETF联接C","code":"002903","category":"broad_index","action":"sell","unit":1,"buy_date":"2018-10-11","buy_adj":0.7602,"sell_adj":0.9958,"return_pct":31.0,"hold_days":503,"tags":[{"rule_id":"SELL_RETURN_30","rule_name":"收益率≥30% 启动减仓","confidence":0.8},{"rule_id":"SELL_RESISTANCE","rule_name":"技术压力位减仓","confidence":0.6}],"primary_tag":"SELL_RETURN_30","sell_streak":2},{"date":"2020-02-26","fund":"广发创业板ETF联接A","code":"003765","category":"broad_index","action":"sell","unit":1,"buy_date":"2017-07-31","buy_adj":0.96,"sell_adj":1.2014,"return_pct":25.1,"hold_days":940,"tags":[{"rule_id":"SELL_RETURN_30","rule_name":"收益率≥30% 启动减仓","confidence":0.55},{"rule_id":"SELL_RESISTANCE","rule_name":"技术压力位减仓","confidence":0.6}],"primary_tag":"SELL_RETURN_30","sell_streak":1},{"date":"2020-03-09","fund":"易方达创业板ETF联接A","code":"110026","category":"broad_index","action":"sell","unit":1,"buy_date":"2018-10-30","buy_adj":1.3342,"sell_adj":2.1254,"return_pct":59.3,"hold_days":496,"tags":[{"rule_id":"SELL_RETURN_60","rule_name":"收益率≥60% 加大减仓","confidence":0.75},{"rule_id":"SELL_RESISTANCE","rule_name":"技术压力位减仓","confidence":0.6}],"primary_tag":"SELL_RETURN_60","sell_streak":2},{"date":"2020-03-09","fund":"广发中证传媒ETF联接A","code":"004752","category":"sector","action":"sell","unit":1,"buy_date":"2018-01-19","buy_adj":0.9959,"sell_adj":0.8646,"return_pct":-13.2,"hold_days":780,"tags":[{"rule_id":"SELL_MECHANICAL","rule_name":"机械执行（兜底标签）","confidence":0.3}],"primary_tag":"SELL_MECHANICAL","sell_streak":1},{"date":"2020-03-11","fund":"华夏海外收益债券A","code":"001061","category":"overseas","action":"sell","unit":1,"buy_date":"2018-04-26","buy_adj":1.35741966,"sell_adj":1.55994031,"return_pct":14.9,"hold_days":685,"tags":[{"rule_id":"SELL_MECHANICAL","rule_name":"机械执行（兜底标签）","confidence":0.3}],"primary_tag":"SELL_MECHANICAL","sell_streak":4},{"date":"2020-03-12","fund":"广发创业板ETF联接A","code":"003765","category":"broad_index","action":"sell","unit":1,"buy_date":"2018-09-28","buy_adj":0.8111,"sell_adj":1.1231,"return_pct":38.5,"hold_days":531,"tags":[{"rule_id":"SELL_RETURN_30","rule_name":"收益率≥30% 启动减仓","confidence":0.8},{"rule_id":"SELL_RESISTANCE","rule_name":"技术压力位减仓","confidence":0.6}],"primary_tag":"SELL_RETURN_30","sell_streak":2},{"date":"2020-03-13","fund":"华安黄金ETF联接A","code":"000216","category":"overseas","action":"sell","unit":1,"buy_date":"2017-09-29","buy_adj":1.029,"sell_adj":1.3007,"return_pct":26.4,"hold_days":896,"tags":[{"rule_id":"SELL_RESISTANCE","rule_name":"技术压力位减仓","confidence":0.6}],"primary_tag":"SELL_RESISTANCE","sell_streak":1},{"date":"2020-03-19","fund":"广发中债7-10年国开债指数A","code":"003376","category":"bond","action":"sell","unit":1,"buy_date":"2017-11-30","buy_adj":0.928,"sell_adj":1.1284,"return_pct":21.6,"hold_days":840,"tags":[{"rule_id":"SELL_RESISTANCE","rule_name":"技术压力位减仓","confidence":0.6}],"primary_tag":"SELL_RESISTANCE","sell_streak":6},{"date":"2020-03-19","fund":"长信可转债债券A","code":"519977","category":"convertible","action":"sell","unit":1,"buy_date":"2019-01-15","buy_adj":2.3225,"sell_adj":2.77981321,"return_pct":19.7,"hold_days":429,"tags":[{"rule_id":"SELL_RESISTANCE","rule_name":"技术压力位减仓","confidence":0.6}],"primary_tag":"SELL_RESISTANCE","sell_streak":1},{"date":"2020-03-25","fund":"广发医药卫生联接A","code":"001180","category":"sector","action":"sell","unit":1,"buy_date":"2016-12-14","buy_adj":0.7895,"sell_adj":0.9164,"return_pct":16.1,"hold_days":1197,"tags":[{"rule_id":"SELL_RESISTANCE","rule_name":"技术压力位减仓","confidence":0.6},{"rule_id":"SELL_GRID_PROFIT","rule_name":"网格波段获利","confidence":0.55}],"primary_tag":"SELL_RESISTANCE","sell_streak":1},{"date":"2020-04-30","fund":"广发医药卫生联接A","code":"001180","category":"sector","action":"sell","unit":1,"buy_date":"2017-01-13","buy_adj":0.7815,"sell_adj":0.9777,"return_pct":25.1,"hold_days":1203,"tags":[{"rule_id":"SELL_RESISTANCE","rule_name":"技术压力位减仓","confidence":0.6}],"primary_tag":"SELL_RESISTANCE","sell_streak":2},{"date":"2020-05-18","fund":"博时标普500ETF联接A","code":"050025","category":"broad_index","action":"sell","unit":1,"buy_date":"2020-03-19","buy_adj":2.03999475,"sell_adj":2.50637824,"return_pct":22.9,"hold_days":60,"tags":[{"rule_id":"SELL_RESISTANCE","rule_name":"技术压力位减仓","confidence":0.6}],"primary_tag":"SELL_RESISTANCE","sell_streak":1},{"date":"2020-05-18","fund":"广发纯债债券A","code":"270048","category":"bond","action":"sell","unit":1,"buy_date":"2017-10-27","buy_adj":1.33,"sell_adj":1.50014765,"return_pct":12.8,"hold_days":934,"tags":[{"rule_id":"SELL_MECHANICAL","rule_name":"机械执行（兜底标签）","confidence":0.3}],"primary_tag":"SELL_MECHANICAL","sell_streak":2},{"date":"2020-06-09","fund":"交银施罗德中证海外中国互联网指数(QDII-LOF)A","code":"164906","category":"overseas","action":"sell","unit":1,"buy_date":"2018-09-04","buy_adj":1.285,"sell_adj":1.577,"return_pct":22.7,"hold_days":644,"tags":[{"rule_id":"SELL_RESISTANCE","rule_name":"技术压力位减仓","confidence":0.6}],"primary_tag":"SELL_RESISTANCE","sell_streak":1},{"date":"2020-06-24","fund":"广发养老指数A","code":"000968","category":"unknown","action":"sell","unit":1,"buy_date":"2016-01-26","buy_adj":0.8507,"sell_adj":1.1545,"return_pct":35.7,"hold_days":1611,"tags":[{"rule_id":"SELL_RESISTANCE","rule_name":"技术压力位减仓","confidence":0.6}],"primary_tag":"SELL_RESISTANCE","sell_streak":1},{"date":"2020-07-10","fund":"广发医药卫生联接A","code":"001180","category":"sector","action":"sell","unit":1,"buy_date":"2017-03-31","buy_adj":0.8153,"sell_adj":1.2708,"return_pct":55.9,"hold_days":1197,"tags":[{"rule_id":"SELL_RESISTANCE","rule_name":"技术压力位减仓","confidence":0.6}],"primary_tag":"SELL_RESISTANCE","sell_streak":3},{"date":"2020-07-16","fund":"广发养老指数A","code":"000968","category":"unknown","action":"sell","unit":1,"buy_date":"2017-01-24","buy_adj":0.9536,"sell_adj":1.2724,"return_pct":33.4,"hold_days":1269,"tags":[{"rule_id":"SELL_RESISTANCE","rule_name":"技术压力位减仓","confidence":0.6}],"primary_tag":"SELL_RESISTANCE","sell_streak":2},{"date":"2020-07-16","fund":"广发医药卫生联接A","code":"001180","category":"sector","action":"sell","unit":1,"buy_date":"2017-04-25","buy_adj":0.8025,"sell_adj":1.2398,"return_pct":54.5,"hold_days":1178,"tags":[{"rule_id":"SELL_RESISTANCE","rule_name":"技术压力位减仓","confidence":0.6}],"primary_tag":"SELL_RESISTANCE","sell_streak":4},{"date":"2020-07-16","fund":"交银施罗德中证海外中国互联网指数(QDII-LOF)A","code":"164906","category":"overseas","action":"sell","unit":1,"buy_date":"2018-11-15","buy_adj":1.158,"sell_adj":1.765,"return_pct":52.4,"hold_days":609,"tags":[{"rule_id":"SELL_RESISTANCE","rule_name":"技术压力位减仓","confidence":0.6}],"primary_tag":"SELL_RESISTANCE","sell_streak":2},{"date":"2020-08-12","fund":"广发养老指数A","code":"000968","category":"unknown","action":"sell","unit":1,"buy_date":"2017-04-14","buy_adj":0.9977,"sell_adj":1.3139,"return_pct":31.7,"hold_days":1216,"tags":[{"rule_id":"SELL_RESISTANCE","rule_name":"技术压力位减仓","confidence":0.6}],"primary_tag":"SELL_RESISTANCE","sell_streak":3},{"date":"2020-08-12","fund":"华夏上证50ETF联接A","code":"001051","category":"broad_index","action":"sell","unit":1,"buy_date":"2015-08-31","buy_adj":0.731,"sell_adj":1.1278,"return_pct":54.3,"hold_days":1808,"tags":[{"rule_id":"SELL_RETURN_30","rule_name":"收益率≥30% 启动减仓","confidence":0.8},{"rule_id":"SELL_RESISTANCE","rule_name":"技术压力位减仓","confidence":0.6}],"primary_tag":"SELL_RETURN_30","sell_streak":2},{"date":"2020-09-11","fund":"广发养老指数A","code":"000968","category":"unknown","action":"sell","unit":1,"buy_date":"2017-04-25","buy_adj":0.9933,"sell_adj":1.2859,"return_pct":29.5,"hold_days":1235,"tags":[{"rule_id":"SELL_RESISTANCE","rule_name":"技术压力位减仓","confidence":0.6}],"primary_tag":"SELL_RESISTANCE","sell_streak":4},{"date":"2020-09-11","fund":"广发医药卫生联接A","code":"001180","category":"sector","action":"sell","unit":1,"buy_date":"2017-04-28","buy_adj":0.802,"sell_adj":1.2325,"return_pct":53.7,"hold_days":1232,"tags":[{"rule_id":"SELL_RESISTANCE","rule_name":"技术压力位减仓","confidence":0.6}],"primary_tag":"SELL_RESISTANCE","sell_streak":5},{"date":"2020-11-11","fund":"交银施罗德中证海外中国互联网指数(QDII-LOF)A","code":"164906","category":"overseas","action":"sell","unit":1,"buy_date":"2019-05-30","buy_adj":1.114,"sell_adj":1.871,"return_pct":68.0,"hold_days":531,"tags":[{"rule_id":"SELL_RESISTANCE","rule_name":"技术压力位减仓","confidence":0.6}],"primary_tag":"SELL_RESISTANCE","sell_streak":3},{"date":"2020-11-13","fund":"博时信用债纯债债券A","code":"050027","category":"bond","action":"sell","unit":1,"buy_date":"2017-10-16","buy_adj":1.4006,"sell_adj":1.59524298,"return_pct":13.9,"hold_days":1124,"tags":[{"rule_id":"SELL_MECHANICAL","rule_name":"机械执行（兜底标签）","confidence":0.3}],"primary_tag":"SELL_MECHANICAL","sell_streak":2},{"date":"2020-12-15","fund":"华夏上证50ETF联接A","code":"001051","category":"broad_index","action":"sell","unit":1,"buy_date":"2015-10-08","buy_adj":0.724,"sell_adj":1.199,"return_pct":65.6,"hold_days":1895,"tags":[{"rule_id":"SELL_RETURN_60","rule_name":"收益率≥60% 加大减仓","confidence":0.95},{"rule_id":"SELL_RESISTANCE","rule_name":"技术压力位减仓","confidence":0.6}],"primary_tag":"SELL_RETURN_60","sell_streak":3},{"date":"2020-12-29","fund":"广发中证环保ETF联接A","code":"001064","category":"sector","action":"sell","unit":1,"buy_date":"2016-04-28","buy_adj":0.7083,"sell_adj":0.8658,"return_pct":22.2,"hold_days":1706,"tags":[{"rule_id":"SELL_RESISTANCE","rule_name":"技术压力位减仓","confidence":0.6},{"rule_id":"SELL_GRID_PROFIT","rule_name":"网格波段获利","confidence":0.55}],"primary_tag":"SELL_RESISTANCE","sell_streak":1},{"date":"2021-01-11","fund":"广发中证环保ETF联接A","code":"001064","category":"sector","action":"sell","unit":1,"buy_date":"2016-11-01","buy_adj":0.7816,"sell_adj":0.9379,"return_pct":20.0,"hold_days":1532,"tags":[{"rule_id":"SELL_RESISTANCE","rule_name":"技术压力位减仓","confidence":0.6},{"rule_id":"SELL_GRID_PROFIT","rule_name":"网格波段获利","confidence":0.55}],"primary_tag":"SELL_RESISTANCE","sell_streak":2},{"date":"2021-01-26","fund":"广发中证环保ETF联接A","code":"001064","category":"sector","action":"sell","unit":1,"buy_date":"2017-09-01","buy_adj":0.7747,"sell_adj":0.9837,"return_pct":27.0,"hold_days":1243,"tags":[{"rule_id":"SELL_RESISTANCE","rule_name":"技术压力位减仓","confidence":0.6}],"primary_tag":"SELL_RESISTANCE","sell_streak":3},{"date":"2021-01-28","fund":"华夏上证50ETF联接A","code":"001051","category":"broad_index","action":"sell","unit":1,"buy_date":"2016-01-26","buy_adj":0.642,"sell_adj":1.2845,"return_pct":100.1,"hold_days":1829,"tags":[{"rule_id":"SELL_RETURN_60","rule_name":"收益率≥60% 加大减仓","confidence":0.95},{"rule_id":"SELL_RESISTANCE","rule_name":"技术压力位减仓","confidence":0.6}],"primary_tag":"SELL_RETURN_60","sell_streak":4},{"date":"2021-01-28","fund":"华安德国(DAX)ETF联接A","code":"000614","category":"unknown","action":"sell","unit":1,"buy_date":"2016-09-13","buy_adj":1.006,"sell_adj":1.322,"return_pct":31.4,"hold_days":1598,"tags":[{"rule_id":"SELL_RESISTANCE","rule_name":"技术压力位减仓","confidence":0.6}],"primary_tag":"SELL_RESISTANCE","sell_streak":1},{"date":"2021-01-29","fund":"华夏沪深300ETF联接A","code":"000051","category":"broad_index","action":"sell","unit":1,"buy_date":"2016-05-30","buy_adj":0.965,"sell_adj":1.7916,"return_pct":85.7,"hold_days":1705,"tags":[{"rule_id":"SELL_RETURN_60","rule_name":"收益率≥60% 加大减仓","confidence":0.95},{"rule_id":"SELL_RESISTANCE","rule_name":"技术压力位减仓","confidence":0.6}],"primary_tag":"SELL_RETURN_60","sell_streak":1},{"date":"2021-02-23","fund":"华夏上证50ETF联接A","code":"001051","category":"broad_index","action":"sell","unit":1,"buy_date":"2016-02-29","buy_adj":0.639,"sell_adj":1.3369,"return_pct":109.2,"hold_days":1821,"tags":[{"rule_id":"SELL_RETURN_60","rule_name":"收益率≥60% 加大减仓","confidence":0.95},{"rule_id":"SELL_RESISTANCE","rule_name":"技术压力位减仓","confidence":0.6}],"primary_tag":"SELL_RETURN_60","sell_streak":5},{"date":"2021-02-24","fund":"华夏恒生ETF联接A","code":"000071","category":"overseas","action":"sell","unit":1,"buy_date":"2015-11-02","buy_adj":1.072,"sell_adj":1.5669,"return_pct":46.2,"hold_days":1941,"tags":[{"rule_id":"SELL_RESISTANCE","rule_name":"技术压力位减仓","confidence":0.6}],"primary_tag":"SELL_RESISTANCE","sell_streak":3},{"date":"2021-03-08","fund":"华安标普全球石油指数(LOF)A","code":"160416","category":"overseas","action":"sell","unit":1,"buy_date":"2015-10-08","buy_adj":0.9052,"sell_adj":1.02578219,"return_pct":13.3,"hold_days":1978,"tags":[{"rule_id":"SELL_MECHANICAL","rule_name":"机械执行（兜底标签）","confidence":0.3}],"primary_tag":"SELL_MECHANICAL","sell_streak":1},{"date":"2021-03-08","fund":"南方原油A","code":"501018","category":"overseas","action":"sell","unit":1,"buy_date":"2020-03-09","buy_adj":0.7162,"sell_adj":0.7534,"return_pct":5.2,"hold_days":364,"tags":[{"rule_id":"SELL_MECHANICAL","rule_name":"机械执行（兜底标签）","confidence":0.3}],"primary_tag":"SELL_MECHANICAL","sell_streak":2},{"date":"2021-03-12","fund":"广发中证环保ETF联接A","code":"001064","category":"sector","action":"sell","unit":1,"buy_date":"2017-11-02","buy_adj":0.805,"sell_adj":0.8771,"return_pct":9.0,"hold_days":1226,"tags":[{"rule_id":"SELL_GRID_PROFIT","rule_name":"网格波段获利","confidence":0.55}],"primary_tag":"SELL_GRID_PROFIT","sell_streak":4},{"date":"2021-04-29","fund":"华安德国(DAX)ETF联接A","code":"000614","category":"unknown","action":"sell","unit":1,"buy_date":"2018-07-16","buy_adj":1.197,"sell_adj":1.448,"return_pct":21.0,"hold_days":1018,"tags":[{"rule_id":"SELL_RESISTANCE","rule_name":"技术压力位减仓","confidence":0.6}],"primary_tag":"SELL_RESISTANCE","sell_streak":2},{"date":"2021-07-20","fund":"广发中证环保ETF联接A","code":"001064","category":"sector","action":"sell","unit":1,"buy_date":"2017-11-30","buy_adj":0.7683,"sell_adj":1.1556,"return_pct":50.4,"hold_days":1328,"tags":[{"rule_id":"SELL_RESISTANCE","rule_name":"技术压力位减仓","confidence":0.6}],"primary_tag":"SELL_RESISTANCE","sell_streak":5},{"date":"2021-08-03","fund":"广发中证环保ETF联接A","code":"001064","category":"sector","action":"sell","unit":1,"buy_date":"2018-02-13","buy_adj":0.6708,"sell_adj":1.1789,"return_pct":75.8,"hold_days":1267,"tags":[{"rule_id":"SELL_RESISTANCE","rule_name":"技术压力位减仓","confidence":0.6}],"primary_tag":"SELL_RESISTANCE","sell_streak":6},{"date":"2021-09-27","fund":"建信中证500指数增强A","code":"000478","category":"broad_index","action":"sell","unit":1,"buy_date":"2017-04-28","buy_adj":2.3018,"sell_adj":3.1654,"return_pct":37.5,"hold_days":1613,"tags":[{"rule_id":"SELL_RETURN_30","rule_name":"收益率≥30% 启动减仓","confidence":0.8},{"rule_id":"SELL_RESISTANCE","rule_name":"技术压力位减仓","confidence":0.6}],"primary_tag":"SELL_RETURN_30","sell_streak":1},{"date":"2021-09-27","fund":"华安德国(DAX)ETF联接A","code":"000614","category":"unknown","action":"sell","unit":1,"buy_date":"2018-11-30","buy_adj":1.079,"sell_adj":1.423,"return_pct":31.9,"hold_days":1032,"tags":[{"rule_id":"SELL_RESISTANCE","rule_name":"技术压力位减仓","confidence":0.6}],"primary_tag":"SELL_RESISTANCE","sell_streak":3},{"date":"2021-12-07","fund":"华宝标普油气上游股票人民币(LOF)A","code":"162411","category":"overseas","action":"sell","unit":1,"buy_date":"2018-11-30","buy_adj":0.567,"sell_adj":0.489,"return_pct":-13.8,"hold_days":1103,"tags":[{"rule_id":"SELL_MECHANICAL","rule_name":"机械执行（兜底标签）","confidence":0.3}],"primary_tag":"SELL_MECHANICAL","sell_streak":3},{"date":"2021-12-17","fund":"广发中证环保ETF联接A","code":"001064","category":"sector","action":"sell","unit":1,"buy_date":"2018-04-26","buy_adj":0.6872,"sell_adj":1.3213,"return_pct":92.3,"hold_days":1331,"tags":[{"rule_id":"SELL_RESISTANCE","rule_name":"技术压力位减仓","confidence":0.6}],"primary_tag":"SELL_RESISTANCE","sell_streak":7},{"date":"2022-01-10","fund":"广发中证500ETF联接C","code":"002903","category":"broad_index","action":"sell","unit":1,"buy_date":"2019-06-18","buy_adj":0.8404,"sell_adj":1.2782,"return_pct":52.1,"hold_days":937,"tags":[{"rule_id":"SELL_RETURN_30","rule_name":"收益率≥30% 启动减仓","confidence":0.8},{"rule_id":"SELL_RESISTANCE","rule_name":"技术压力位减仓","confidence":0.6}],"primary_tag":"SELL_RETURN_30","sell_streak":3},{"date":"2022-01-19","fund":"华安德国(DAX)ETF联接A","code":"000614","category":"unknown","action":"sell","unit":1,"buy_date":"2019-03-28","buy_adj":1.052,"sell_adj":1.361,"return_pct":29.4,"hold_days":1028,"tags":[{"rule_id":"SELL_RESISTANCE","rule_name":"技术压力位减仓","confidence":0.6}],"primary_tag":"SELL_RESISTANCE","sell_streak":4},{"date":"2022-02-11","fund":"广发中债7-10年国开债指数A","code":"003376","category":"bond","action":"sell","unit":1,"buy_date":"2020-12-15","buy_adj":1.12791578,"sell_adj":1.21658174,"return_pct":7.9,"hold_days":423,"tags":[{"rule_id":"SELL_MECHANICAL","rule_name":"机械执行（兜底标签）","confidence":0.3}],"primary_tag":"SELL_MECHANICAL","sell_streak":7},{"date":"2022-02-28","fund":"兴全可转债混合","code":"340001","category":"convertible","action":"sell","unit":1,"buy_date":"2018-05-31","buy_adj":7.5355,"sell_adj":11.85719442,"return_pct":57.4,"hold_days":1369,"tags":[{"rule_id":"SELL_RESISTANCE","rule_name":"技术压力位减仓","confidence":0.6}],"primary_tag":"SELL_RESISTANCE","sell_streak":1},{"date":"2022-02-28","fund":"广发中证环保ETF联接A","code":"001064","category":"sector","action":"sell","unit":1,"buy_date":"2018-06-28","buy_adj":0.5915,"sell_adj":1.2122,"return_pct":104.9,"hold_days":1341,"tags":[{"rule_id":"SELL_RESISTANCE","rule_name":"技术压力位减仓","confidence":0.6}],"primary_tag":"SELL_RESISTANCE","sell_streak":8},{"date":"2022-03-07","fund":"富国中证红利指数增强A","code":"100032","category":"dividend","action":"sell","unit":1,"buy_date":"2016-12-14","buy_adj":2.89645952,"sell_adj":4.57932224,"return_pct":58.1,"hold_days":1909,"tags":[{"rule_id":"SELL_RESISTANCE","rule_name":"技术压力位减仓","confidence":0.6}],"primary_tag":"SELL_RESISTANCE","sell_streak":1},{"date":"2022-03-10","fund":"华宝标普油气上游股票人民币(LOF)A","code":"162411","category":"overseas","action":"sell","unit":1,"buy_date":"2018-12-27","buy_adj":0.467,"sell_adj":0.6037,"return_pct":29.3,"hold_days":1169,"tags":[{"rule_id":"SELL_RESISTANCE","rule_name":"技术压力位减仓","confidence":0.6}],"primary_tag":"SELL_RESISTANCE","sell_streak":4},{"date":"2022-03-15","fund":"易方达安心债券A","code":"110027","category":"unknown","action":"sell","unit":1,"buy_date":"2019-01-31","buy_adj":2.6671,"sell_adj":3.56464355,"return_pct":33.6,"hold_days":1139,"tags":[{"rule_id":"SELL_RESISTANCE","rule_name":"技术压力位减仓","confidence":0.6}],"primary_tag":"SELL_RESISTANCE","sell_streak":1},{"date":"2022-03-15","fund":"南方通利A","code":"000563","category":"unknown","action":"sell","unit":1,"buy_date":"2020-09-01","buy_adj":1.4617379,"sell_adj":1.55059761,"return_pct":6.1,"hold_days":560,"tags":[{"rule_id":"SELL_MECHANICAL","rule_name":"机械执行（兜底标签）","confidence":0.3}],"primary_tag":"SELL_MECHANICAL","sell_streak":1},{"date":"2022-03-18","fund":"广发中证环保ETF联接A","code":"001064","category":"sector","action":"sell","unit":1,"buy_date":"2018-10-15","buy_adj":0.4769,"sell_adj":1.1557,"return_pct":142.3,"hold_days":1250,"tags":[{"rule_id":"SELL_RESISTANCE","rule_name":"技术压力位减仓","confidence":0.6}],"primary_tag":"SELL_RESISTANCE","sell_streak":9},{"date":"2022-04-14","fund":"易方达安心债券A","code":"110027","category":"unknown","action":"sell","unit":1,"buy_date":"2019-05-15","buy_adj":2.8428,"sell_adj":3.6028908,"return_pct":26.7,"hold_days":1065,"tags":[{"rule_id":"SELL_RESISTANCE","rule_name":"技术压力位减仓","confidence":0.6}],"primary_tag":"SELL_RESISTANCE","sell_streak":2},{"date":"2022-04-22","fund":"华宝标普油气上游股票人民币(LOF)A","code":"162411","category":"overseas","action":"sell","unit":1,"buy_date":"2019-03-28","buy_adj":0.519,"sell_adj":0.6432,"return_pct":23.9,"hold_days":1121,"tags":[{"rule_id":"SELL_RESISTANCE","rule_name":"技术压力位减仓","confidence":0.6}],"primary_tag":"SELL_RESISTANCE","sell_streak":5},{"date":"2022-04-26","fund":"易方达高等级信用债A","code":"000147","category":"bond","action":"sell","unit":1,"buy_date":"2020-10-13","buy_adj":1.428635,"sell_adj":1.49406393,"return_pct":4.6,"hold_days":560,"tags":[{"rule_id":"SELL_MECHANICAL","rule_name":"机械执行（兜底标签）","confidence":0.3}],"primary_tag":"SELL_MECHANICAL","sell_streak":1},{"date":"2022-05-16","fund":"广发中证500ETF联接C","code":"002903","category":"broad_index","action":"sell","unit":1,"buy_date":"2022-04-26","buy_adj":0.9446,"sell_adj":1.0388,"return_pct":10.0,"hold_days":20,"tags":[{"rule_id":"SELL_MECHANICAL","rule_name":"机械执行（兜底标签）","confidence":0.3}],"primary_tag":"SELL_MECHANICAL","sell_streak":4},{"date":"2022-05-31","fund":"广发中债7-10年国开债指数A","code":"003376","category":"bond","action":"sell","unit":1,"buy_date":"2020-12-29","buy_adj":1.133672,"sell_adj":1.23001291,"return_pct":8.5,"hold_days":518,"tags":[{"rule_id":"SELL_MECHANICAL","rule_name":"机械执行（兜底标签）","confidence":0.3}],"primary_tag":"SELL_MECHANICAL","sell_streak":8},{"date":"2022-06-21","fund":"华安德国(DAX)ETF联接A","code":"000614","category":"unknown","action":"sell","unit":1,"buy_date":"2020-03-11","buy_adj":0.978,"sell_adj":1.099,"return_pct":12.4,"hold_days":832,"tags":[{"rule_id":"SELL_MECHANICAL","rule_name":"机械执行（兜底标签）","confidence":0.3}],"primary_tag":"SELL_MECHANICAL","sell_streak":5},{"date":"2022-07-05","fund":"华夏上证50ETF联接A","code":"001051","category":"broad_index","action":"sell","unit":1,"buy_date":"2016-03-31","buy_adj":0.703,"sell_adj":1.0789211,"return_pct":53.5,"hold_days":2287,"tags":[{"rule_id":"SELL_RETURN_30","rule_name":"收益率≥30% 启动减仓","confidence":0.8},{"rule_id":"SELL_RESISTANCE","rule_name":"技术压力位减仓","confidence":0.6}],"primary_tag":"SELL_RETURN_30","sell_streak":6},{"date":"2022-09-23","fund":"南方通利A","code":"000563","category":"unknown","action":"sell","unit":1,"buy_date":"2020-10-30","buy_adj":1.46957528,"sell_adj":1.57974457,"return_pct":7.5,"hold_days":693,"tags":[{"rule_id":"SELL_MECHANICAL","rule_name":"机械执行（兜底标签）","confidence":0.3}],"primary_tag":"SELL_MECHANICAL","sell_streak":2},{"date":"2022-10-31","fund":"广发纯债债券A","code":"270048","category":"bond","action":"sell","unit":1,"buy_date":"2020-06-24","buy_adj":1.49400453,"sell_adj":1.66113186,"return_pct":11.2,"hold_days":859,"tags":[{"rule_id":"SELL_MECHANICAL","rule_name":"机械执行（兜底标签）","confidence":0.3}],"primary_tag":"SELL_MECHANICAL","sell_streak":3},{"date":"2022-11-10","fund":"南方通利A","code":"000563","category":"unknown","action":"sell","unit":1,"buy_date":"2020-10-30","buy_adj":1.46957528,"sell_adj":1.55229291,"return_pct":5.6,"hold_days":741,"tags":[{"rule_id":"SELL_MECHANICAL","rule_name":"机械执行（兜底标签）","confidence":0.3}],"primary_tag":"SELL_MECHANICAL","sell_streak":3},{"date":"2022-11-17","fund":"融通健康产业灵活配置混合A","code":"000727","category":"sector","action":"sell","unit":1,"buy_date":"2022-09-23","buy_adj":2.616,"sell_adj":3.438,"return_pct":31.4,"hold_days":55,"tags":[{"rule_id":"SELL_RESISTANCE","rule_name":"技术压力位减仓","confidence":0.6}],"primary_tag":"SELL_RESISTANCE","sell_streak":1},{"date":"2022-12-20","fund":"广发生物科技指数(QDII)A","code":"001092","category":"overseas","action":"sell","unit":1,"buy_date":"2022-07-01","buy_adj":1.006,"sell_adj":1.128,"return_pct":12.1,"hold_days":172,"tags":[{"rule_id":"SELL_MECHANICAL","rule_name":"机械执行（兜底标签）","confidence":0.3}],"primary_tag":"SELL_MECHANICAL","sell_streak":1},{"date":"2023-01-06","fund":"易方达消费行业","code":"110022","category":"sector","action":"sell","unit":1,"buy_date":"2022-05-31","buy_adj":3.925,"sell_adj":4.159,"return_pct":6.0,"hold_days":220,"tags":[{"rule_id":"SELL_MECHANICAL","rule_name":"机械执行（兜底标签）","confidence":0.3}],"primary_tag":"SELL_MECHANICAL","sell_streak":2},{"date":"2023-02-01","fund":"建信中证500指数增强A","code":"000478","category":"broad_index","action":"sell","unit":1,"buy_date":"2017-09-01","buy_adj":2.4583,"sell_adj":2.8673,"return_pct":16.6,"hold_days":1979,"tags":[{"rule_id":"SELL_RESISTANCE","rule_name":"技术压力位减仓","confidence":0.6}],"primary_tag":"SELL_RESISTANCE","sell_streak":2},{"date":"2023-02-01","fund":"易方达中证全指证券公司指数(LOF)A","code":"502010","category":"sector","action":"sell","unit":1,"buy_date":"2017-12-14","buy_adj":0.70112434,"sell_adj":0.7721113,"return_pct":10.1,"hold_days":1875,"tags":[{"rule_id":"SELL_GRID_PROFIT","rule_name":"网格波段获利","confidence":0.55}],"primary_tag":"SELL_GRID_PROFIT","sell_streak":1},{"date":"2023-02-01","fund":"博时恒生医疗保健ETF发起式联接(QDII)A","code":"014424","category":"overseas","action":"sell","unit":1,"buy_date":"2022-05-31","buy_adj":0.8007,"sell_adj":1.0266,"return_pct":28.2,"hold_days":246,"tags":[{"rule_id":"SELL_RESISTANCE","rule_name":"技术压力位减仓","confidence":0.6}],"primary_tag":"SELL_RESISTANCE","sell_streak":1},{"date":"2023-02-23","fund":"富国消费主题混合A","code":"519915","category":"sector","action":"sell","unit":1,"buy_date":"2021-09-03","buy_adj":2.827,"sell_adj":2.864,"return_pct":1.3,"hold_days":538,"tags":[{"rule_id":"SELL_MECHANICAL","rule_name":"机械执行（兜底标签）","confidence":0.3}],"primary_tag":"SELL_MECHANICAL","sell_streak":1},{"date":"2023-02-27","fund":"华夏中证500ETF联接A","code":"001052","category":"broad_index","action":"sell","unit":1,"buy_date":"2016-02-29","buy_adj":0.572,"sell_adj":0.7289,"return_pct":27.4,"hold_days":2555,"tags":[{"rule_id":"SELL_RETURN_30","rule_name":"收益率≥30% 启动减仓","confidence":0.55},{"rule_id":"SELL_RESISTANCE","rule_name":"技术压力位减仓","confidence":0.6}],"primary_tag":"SELL_RETURN_30","sell_streak":1},{"date":"2023-03-14","fund":"华安德国(DAX)ETF联接A","code":"000614","category":"unknown","action":"sell","unit":1,"buy_date":"2020-03-13","buy_adj":0.913,"sell_adj":1.288,"return_pct":41.1,"hold_days":1096,"tags":[{"rule_id":"SELL_RESISTANCE","rule_name":"技术压力位减仓","confidence":0.6}],"primary_tag":"SELL_RESISTANCE","sell_streak":6},{"date":"2023-03-20","fund":"广发中证传媒ETF联接A","code":"004752","category":"sector","action":"sell","unit":1,"buy_date":"2018-01-19","buy_adj":0.9959,"sell_adj":0.7558,"return_pct":-24.1,"hold_days":1886,"tags":[{"rule_id":"SELL_MECHANICAL","rule_name":"机械执行（兜底标签）","confidence":0.3}],"primary_tag":"SELL_MECHANICAL","sell_streak":2},{"date":"2023-03-23","fund":"广发信息技术联接A","code":"000942","category":"unknown","action":"sell","unit":1,"buy_date":"2021-04-29","buy_adj":1.2157,"sell_adj":1.1721,"return_pct":-3.6,"hold_days":693,"tags":[{"rule_id":"SELL_MECHANICAL","rule_name":"机械执行（兜底标签）","confidence":0.3}],"primary_tag":"SELL_MECHANICAL","sell_streak":1},{"date":"2023-04-03","fund":"广发中证传媒ETF联接A","code":"004752","category":"sector","action":"sell","unit":1,"buy_date":"2018-05-15","buy_adj":0.9344,"sell_adj":0.8913,"return_pct":-4.6,"hold_days":1784,"tags":[{"rule_id":"SELL_MECHANICAL","rule_name":"机械执行（兜底标签）","confidence":0.3}],"primary_tag":"SELL_MECHANICAL","sell_streak":3},{"date":"2023-04-14","fund":"广发中证传媒ETF联接A","code":"004752","category":"sector","action":"sell","unit":1,"buy_date":"2018-07-16","buy_adj":0.8029,"sell_adj":0.9018,"return_pct":12.3,"hold_days":1733,"tags":[{"rule_id":"SELL_GRID_PROFIT","rule_name":"网格波段获利","confidence":0.55}],"primary_tag":"SELL_GRID_PROFIT","sell_streak":4},{"date":"2023-05-31","fund":"广发中证传媒ETF联接A","code":"004752","category":"sector","action":"sell","unit":1,"buy_date":"2018-08-20","buy_adj":0.728,"sell_adj":0.9208,"return_pct":26.5,"hold_days":1745,"tags":[{"rule_id":"SELL_RESISTANCE","rule_name":"技术压力位减仓","confidence":0.6}],"primary_tag":"SELL_RESISTANCE","sell_streak":5},{"date":"2023-05-31","fund":"广发中证传媒ETF联接A","code":"004752","category":"sector","action":"sell","unit":1,"buy_date":"2019-04-26","buy_adj":0.814,"sell_adj":0.9208,"return_pct":13.1,"hold_days":1496,"tags":[{"rule_id":"SELL_GRID_PROFIT","rule_name":"网格波段获利","confidence":0.55}],"primary_tag":"SELL_GRID_PROFIT","sell_streak":6},{"date":"2023-06-20","fund":"易方达信息产业混合A","code":"001513","category":"unknown","action":"sell","unit":1,"buy_date":"2022-04-12","buy_adj":2.221,"sell_adj":2.869,"return_pct":29.2,"hold_days":434,"tags":[{"rule_id":"SELL_RESISTANCE","rule_name":"技术压力位减仓","confidence":0.6}],"primary_tag":"SELL_RESISTANCE","sell_streak":1},{"date":"2023-08-08","fund":"易方达中证全指证券公司指数(LOF)A","code":"502010","category":"sector","action":"sell","unit":1,"buy_date":"2018-04-02","buy_adj":0.64231292,"sell_adj":0.83160969,"return_pct":29.5,"hold_days":1954,"tags":[{"rule_id":"SELL_RESISTANCE","rule_name":"技术压力位减仓","confidence":0.6}],"primary_tag":"SELL_RESISTANCE","sell_streak":2},{"date":"2023-08-10","fund":"广发纳指100ETF联接人民币(QDII)A","code":"270042","category":"broad_index","action":"sell","unit":1,"buy_date":"2022-11-16","buy_adj":4.3428791,"sell_adj":5.65466747,"return_pct":30.2,"hold_days":267,"tags":[{"rule_id":"SELL_RETURN_30","rule_name":"收益率≥30% 启动减仓","confidence":0.8},{"rule_id":"SELL_RESISTANCE","rule_name":"技术压力位减仓","confidence":0.6}],"primary_tag":"SELL_RETURN_30","sell_streak":1},{"date":"2023-08-18","fund":"博时标普500ETF联接A","code":"050025","category":"broad_index","action":"sell","unit":1,"buy_date":"2022-06-21","buy_adj":2.97822019,"sell_adj":3.66556637,"return_pct":23.1,"hold_days":423,"tags":[{"rule_id":"SELL_RESISTANCE","rule_name":"技术压力位减仓","confidence":0.6}],"primary_tag":"SELL_RESISTANCE","sell_streak":2},{"date":"2023-12-05","fund":"华安黄金ETF联接A","code":"000216","category":"overseas","action":"sell","unit":1,"buy_date":"2019-07-01","buy_adj":1.1296,"sell_adj":1.6908,"return_pct":49.7,"hold_days":1618,"tags":[{"rule_id":"SELL_RESISTANCE","rule_name":"技术压力位减仓","confidence":0.6}],"primary_tag":"SELL_RESISTANCE","sell_streak":2},{"date":"2024-02-28","fund":"广发中证500ETF联接C","code":"002903","category":"broad_index","action":"sell","unit":1,"buy_date":"2024-01-22","buy_adj":0.8888,"sell_adj":0.9621,"return_pct":8.2,"hold_days":37,"tags":[{"rule_id":"SELL_MECHANICAL","rule_name":"机械执行（兜底标签）","confidence":0.3}],"primary_tag":"SELL_MECHANICAL","sell_streak":5},{"date":"2024-03-07","fund":"富国中证红利指数增强A","code":"100032","category":"dividend","action":"sell","unit":1,"buy_date":"2016-12-29","buy_adj":2.85270006,"sell_adj":5.09255281,"return_pct":78.5,"hold_days":2625,"tags":[{"rule_id":"SELL_RESISTANCE","rule_name":"技术压力位减仓","confidence":0.6}],"primary_tag":"SELL_RESISTANCE","sell_streak":2},{"date":"2024-04-18","fund":"广发纳指100ETF联接人民币(QDII)A","code":"270042","category":"broad_index","action":"sell","unit":1,"buy_date":"2023-01-03","buy_adj":3.98297132,"sell_adj":6.39311154,"return_pct":60.5,"hold_days":471,"tags":[{"rule_id":"SELL_RETURN_60","rule_name":"收益率≥60% 加大减仓","confidence":0.95},{"rule_id":"SELL_RESISTANCE","rule_name":"技术压力位减仓","confidence":0.6}],"primary_tag":"SELL_RETURN_60","sell_streak":2},{"date":"2024-05-06","fund":"富国消费主题混合C","code":"011309","category":"sector","action":"sell","unit":1,"buy_date":"2023-05-26","buy_adj":2.534,"sell_adj":2.483,"return_pct":-2.0,"hold_days":346,"tags":[{"rule_id":"SELL_MECHANICAL","rule_name":"机械执行（兜底标签）","confidence":0.3}],"primary_tag":"SELL_MECHANICAL","sell_streak":1},{"date":"2024-05-17","fund":"华夏恒生ETF联接A","code":"000071","category":"overseas","action":"sell","unit":1,"buy_date":"2015-11-30","buy_adj":1.069,"sell_adj":1.1716,"return_pct":9.6,"hold_days":3091,"tags":[{"rule_id":"SELL_MECHANICAL","rule_name":"机械执行（兜底标签）","confidence":0.3}],"primary_tag":"SELL_MECHANICAL","sell_streak":4},{"date":"2024-09-24","fund":"华夏恒生ETF联接A","code":"000071","category":"overseas","action":"sell","unit":1,"buy_date":"2015-12-29","buy_adj":1.083,"sell_adj":1.1587,"return_pct":7.0,"hold_days":3192,"tags":[{"rule_id":"SELL_MECHANICAL","rule_name":"机械执行（兜底标签）","confidence":0.3}],"primary_tag":"SELL_MECHANICAL","sell_streak":5},{"date":"2024-09-30","fund":"广发中证全指金融地产联接A","code":"001469","category":"sector","action":"sell","unit":1,"buy_date":"2018-06-14","buy_adj":0.944,"sell_adj":1.1948,"return_pct":26.6,"hold_days":2300,"tags":[{"rule_id":"SELL_RESISTANCE","rule_name":"技术压力位减仓","confidence":0.6}],"primary_tag":"SELL_RESISTANCE","sell_streak":1},{"date":"2024-09-30","fund":"华夏沪深300ETF联接C","code":"005658","category":"broad_index","action":"sell","unit":1,"buy_date":"2023-10-20","buy_adj":1.2451,"sell_adj":1.4453,"return_pct":16.1,"hold_days":346,"tags":[{"rule_id":"SELL_RESISTANCE","rule_name":"技术压力位减仓","confidence":0.6}],"primary_tag":"SELL_RESISTANCE","sell_streak":1},{"date":"2024-10-08","fund":"华夏恒生ETF联接A","code":"000071","category":"overseas","action":"sell","unit":1,"buy_date":"2015-12-29","buy_adj":1.083,"sell_adj":1.2743,"return_pct":17.7,"hold_days":3206,"tags":[{"rule_id":"SELL_RESISTANCE","rule_name":"技术压力位减仓","confidence":0.6}],"primary_tag":"SELL_RESISTANCE","sell_streak":6},{"date":"2024-10-08","fund":"华夏中证500ETF联接A","code":"001052","category":"broad_index","action":"sell","unit":1,"buy_date":"2017-05-23","buy_adj":0.613,"sell_adj":0.7312,"return_pct":19.3,"hold_days":2695,"tags":[{"rule_id":"SELL_RESISTANCE","rule_name":"技术压力位减仓","confidence":0.6}],"primary_tag":"SELL_RESISTANCE","sell_streak":2},{"date":"2024-10-21","fund":"广发信息技术联接A","code":"000942","category":"unknown","action":"sell","unit":1,"buy_date":"2022-04-22","buy_adj":0.9599,"sell_adj":1.1538,"return_pct":20.2,"hold_days":913,"tags":[{"rule_id":"SELL_RESISTANCE","rule_name":"技术压力位减仓","confidence":0.6}],"primary_tag":"SELL_RESISTANCE","sell_streak":2},{"date":"2024-11-06","fund":"广发中证全指金融地产联接A","code":"001469","category":"sector","action":"sell","unit":1,"buy_date":"2018-06-28","buy_adj":0.866,"sell_adj":1.2453,"return_pct":43.8,"hold_days":2323,"tags":[{"rule_id":"SELL_RESISTANCE","rule_name":"技术压力位减仓","confidence":0.6}],"primary_tag":"SELL_RESISTANCE","sell_streak":2},{"date":"2024-11-11","fund":"易方达中证全指证券公司指数(LOF)A","code":"502010","category":"sector","action":"sell","unit":1,"buy_date":"2018-06-19","buy_adj":0.54179537,"sell_adj":1.02966411,"return_pct":90.0,"hold_days":2337,"tags":[{"rule_id":"SELL_RESISTANCE","rule_name":"技术压力位减仓","confidence":0.6}],"primary_tag":"SELL_RESISTANCE","sell_streak":3},{"date":"2024-11-12","fund":"广发信息技术联接A","code":"000942","category":"unknown","action":"sell","unit":1,"buy_date":"2022-04-26","buy_adj":0.8734,"sell_adj":1.2672,"return_pct":45.1,"hold_days":931,"tags":[{"rule_id":"SELL_RESISTANCE","rule_name":"技术压力位减仓","confidence":0.6}],"primary_tag":"SELL_RESISTANCE","sell_streak":3},{"date":"2024-12-10","fund":"天弘恒生科技指数联接(QDII)A","code":"012348","category":"overseas","action":"sell","unit":1,"buy_date":"2021-12-16","buy_adj":0.7678,"sell_adj":0.6733,"return_pct":-12.3,"hold_days":1090,"tags":[{"rule_id":"SELL_MECHANICAL","rule_name":"机械执行（兜底标签）","confidence":0.3}],"primary_tag":"SELL_MECHANICAL","sell_streak":1},{"date":"2024-12-10","fund":"广发中证全指金融地产联接A","code":"001469","category":"sector","action":"sell","unit":1,"buy_date":"2018-09-21","buy_adj":0.9303,"sell_adj":1.2425,"return_pct":33.6,"hold_days":2272,"tags":[{"rule_id":"SELL_RESISTANCE","rule_name":"技术压力位减仓","confidence":0.6}],"primary_tag":"SELL_RESISTANCE","sell_streak":3},{"date":"2025-02-20","fund":"华夏恒生ETF联接A","code":"000071","category":"overseas","action":"sell","unit":1,"buy_date":"2016-01-26","buy_adj":0.942,"sell_adj":1.391,"return_pct":47.7,"hold_days":3313,"tags":[{"rule_id":"SELL_RESISTANCE","rule_name":"技术压力位减仓","confidence":0.6}],"primary_tag":"SELL_RESISTANCE","sell_streak":7},{"date":"2025-03-07","fund":"天弘恒生科技指数联接(QDII)A","code":"012348","category":"overseas","action":"sell","unit":1,"buy_date":"2022-02-09","buy_adj":0.7464,"sell_adj":0.8775,"return_pct":17.6,"hold_days":1122,"tags":[{"rule_id":"SELL_RESISTANCE","rule_name":"技术压力位减仓","confidence":0.6}],"primary_tag":"SELL_RESISTANCE","sell_streak":2},{"date":"2025-04-23","fund":"天弘恒生科技指数联接(QDII)A","code":"012348","category":"overseas","action":"sell","unit":1,"buy_date":"2022-03-18","buy_adj":0.5984,"sell_adj":0.7449,"return_pct":24.5,"hold_days":1132,"tags":[{"rule_id":"SELL_RESISTANCE","rule_name":"技术压力位减仓","confidence":0.6}],"primary_tag":"SELL_RESISTANCE","sell_streak":3},{"date":"2025-04-25","fund":"博时恒生医疗保健ETF发起式联接(QDII)A","code":"014424","category":"overseas","action":"sell","unit":1,"buy_date":"2023-02-27","buy_adj":0.9198,"sell_adj":0.7772,"return_pct":-15.5,"hold_days":788,"tags":[{"rule_id":"SELL_MECHANICAL","rule_name":"机械执行（兜底标签）","confidence":0.3}],"primary_tag":"SELL_MECHANICAL","sell_streak":2},{"date":"2025-05-06","fund":"广发纳指100ETF联接人民币(QDII)A","code":"270042","category":"broad_index","action":"sell","unit":1,"buy_date":"2025-04-09","buy_adj":7.01832347,"sell_adj":7.22591574,"return_pct":3.0,"hold_days":27,"tags":[{"rule_id":"SELL_MECHANICAL","rule_name":"机械执行（兜底标签）","confidence":0.3}],"primary_tag":"SELL_MECHANICAL","sell_streak":3},{"date":"2025-07-14","fund":"广发中证全指金融地产联接A","code":"001469","category":"sector","action":"sell","unit":1,"buy_date":"2020-02-26","buy_adj":1.0894,"sell_adj":1.3412,"return_pct":23.1,"hold_days":1965,"tags":[{"rule_id":"SELL_RESISTANCE","rule_name":"技术压力位减仓","confidence":0.6},{"rule_id":"SELL_GRID_PROFIT","rule_name":"网格波段获利","confidence":0.55}],"primary_tag":"SELL_RESISTANCE","sell_streak":4},{"date":"2025-07-22","fund":"博时恒生医疗保健ETF发起式联接(QDII)A","code":"014424","category":"overseas","action":"sell","unit":1,"buy_date":"2024-08-13","buy_adj":0.5754,"sell_adj":1.0096,"return_pct":75.5,"hold_days":343,"tags":[{"rule_id":"SELL_RESISTANCE","rule_name":"技术压力位减仓","confidence":0.6}],"primary_tag":"SELL_RESISTANCE","sell_streak":3},{"date":"2025-08-13","fund":"建信中证500指数增强A","code":"000478","category":"broad_index","action":"sell","unit":1,"buy_date":"2017-09-29","buy_adj":2.4887,"sell_adj":3.0044,"return_pct":20.7,"hold_days":2875,"tags":[{"rule_id":"SELL_RESISTANCE","rule_name":"技术压力位减仓","confidence":0.6}],"primary_tag":"SELL_RESISTANCE","sell_streak":3},{"date":"2025-08-22","fund":"广发中证传媒ETF联接A","code":"004752","category":"sector","action":"sell","unit":1,"buy_date":"2021-04-29","buy_adj":0.8067,"sell_adj":0.9836,"return_pct":21.9,"hold_days":1576,"tags":[{"rule_id":"SELL_RESISTANCE","rule_name":"技术压力位减仓","confidence":0.6},{"rule_id":"SELL_GRID_PROFIT","rule_name":"网格波段获利","confidence":0.55}],"primary_tag":"SELL_RESISTANCE","sell_streak":7},{"date":"2025-09-01","fund":"华夏上证50ETF联接A","code":"001051","category":"broad_index","action":"sell","unit":1,"buy_date":"2016-04-28","buy_adj":0.698,"sell_adj":1.1441,"return_pct":63.9,"hold_days":3413,"tags":[{"rule_id":"SELL_RETURN_60","rule_name":"收益率≥60% 加大减仓","confidence":0.95},{"rule_id":"SELL_RESISTANCE","rule_name":"技术压力位减仓","confidence":0.6}],"primary_tag":"SELL_RETURN_60","sell_streak":7},{"date":"2025-09-12","fund":"华夏恒生ETF联接A","code":"000071","category":"overseas","action":"sell","unit":1,"buy_date":"2016-01-26","buy_adj":0.942,"sell_adj":1.6203,"return_pct":72.0,"hold_days":3517,"tags":[{"rule_id":"SELL_RESISTANCE","rule_name":"技术压力位减仓","confidence":0.6}],"primary_tag":"SELL_RESISTANCE","sell_streak":8},{"date":"2025-10-24","fund":"广发创业板ETF联接A","code":"003765","category":"broad_index","action":"sell","unit":1,"buy_date":"2024-01-10","buy_adj":0.9562,"sell_adj":1.7289,"return_pct":80.8,"hold_days":653,"tags":[{"rule_id":"SELL_RETURN_60","rule_name":"收益率≥60% 加大减仓","confidence":0.95},{"rule_id":"SELL_RESISTANCE","rule_name":"技术压力位减仓","confidence":0.6}],"primary_tag":"SELL_RETURN_60","sell_streak":3},{"date":"2025-11-21","fund":"华夏恒生ETF联接A","code":"000071","category":"overseas","action":"sell","unit":1,"buy_date":"2016-02-29","buy_adj":0.954,"sell_adj":1.5492,"return_pct":62.4,"hold_days":3553,"tags":[{"rule_id":"SELL_RESISTANCE","rule_name":"技术压力位减仓","confidence":0.6}],"primary_tag":"SELL_RESISTANCE","sell_streak":9},{"date":"2025-11-25","fund":"富国中证500指数增强A","code":"161017","category":"broad_index","action":"sell","unit":1,"buy_date":"2018-08-01","buy_adj":1.949,"sell_adj":3.32453825,"return_pct":70.6,"hold_days":2673,"tags":[{"rule_id":"SELL_RETURN_60","rule_name":"收益率≥60% 加大减仓","confidence":0.95},{"rule_id":"SELL_RESISTANCE","rule_name":"技术压力位减仓","confidence":0.6}],"primary_tag":"SELL_RETURN_60","sell_streak":1},{"date":"2026-01-07","fund":"华夏中证500ETF联接A","code":"001052","category":"broad_index","action":"sell","unit":1,"buy_date":"2017-11-02","buy_adj":0.689,"sell_adj":0.9424,"return_pct":36.8,"hold_days":2988,"tags":[{"rule_id":"SELL_RETURN_30","rule_name":"收益率≥30% 启动减仓","confidence":0.8},{"rule_id":"SELL_RESISTANCE","rule_name":"技术压力位减仓","confidence":0.6}],"primary_tag":"SELL_RETURN_30","sell_streak":3},{"date":"2026-01-07","fund":"建信中证500指数增强A","code":"000478","category":"broad_index","action":"sell","unit":1,"buy_date":"2017-10-27","buy_adj":2.5004,"sell_adj":3.4908,"return_pct":39.6,"hold_days":2994,"tags":[{"rule_id":"SELL_RETURN_30","rule_name":"收益率≥30% 启动减仓","confidence":0.8},{"rule_id":"SELL_RESISTANCE","rule_name":"技术压力位减仓","confidence":0.6}],"primary_tag":"SELL_RETURN_30","sell_streak":4},{"date":"2026-01-09","fund":"建信中证500指数增强A","code":"000478","category":"broad_index","action":"sell","unit":1,"buy_date":"2017-11-30","buy_adj":2.3535,"sell_adj":3.5396,"return_pct":50.4,"hold_days":2962,"tags":[{"rule_id":"SELL_RETURN_30","rule_name":"收益率≥30% 启动减仓","confidence":0.8},{"rule_id":"SELL_RESISTANCE","rule_name":"技术压力位减仓","confidence":0.6}],"primary_tag":"SELL_RETURN_30","sell_streak":5},{"date":"2026-01-13","fund":"华宝医疗ETF联接C","code":"012323","category":"sector","action":"sell","unit":1,"buy_date":"2023-04-26","buy_adj":0.7916,"sell_adj":0.6637,"return_pct":-16.2,"hold_days":993,"tags":[{"rule_id":"SELL_MECHANICAL","rule_name":"机械执行（兜底标签）","confidence":0.3}],"primary_tag":"SELL_MECHANICAL","sell_streak":1},{"date":"2026-01-15","fund":"广发中证传媒ETF联接A","code":"004752","category":"sector","action":"sell","unit":1,"buy_date":"2021-08-30","buy_adj":0.6802,"sell_adj":1.2422,"return_pct":82.6,"hold_days":1599,"tags":[{"rule_id":"SELL_RESISTANCE","rule_name":"技术压力位减仓","confidence":0.6}],"primary_tag":"SELL_RESISTANCE","sell_streak":8},{"date":"2026-01-23","fund":"富国中证500指数增强A","code":"161017","category":"broad_index","action":"sell","unit":1,"buy_date":"2018-09-03","buy_adj":1.863,"sell_adj":3.98036091,"return_pct":113.7,"hold_days":2699,"tags":[{"rule_id":"SELL_RETURN_60","rule_name":"收益率≥60% 加大减仓","confidence":0.95},{"rule_id":"SELL_RESISTANCE","rule_name":"技术压力位减仓","confidence":0.6}],"primary_tag":"SELL_RETURN_60","sell_streak":2},{"date":"2026-01-30","fund":"华夏中证500ETF联接A","code":"001052","category":"broad_index","action":"sell","unit":1,"buy_date":"2018-05-15","buy_adj":0.644,"sell_adj":0.9995,"return_pct":55.2,"hold_days":2817,"tags":[{"rule_id":"SELL_RETURN_60","rule_name":"收益率≥60% 加大减仓","confidence":0.75},{"rule_id":"SELL_RESISTANCE","rule_name":"技术压力位减仓","confidence":0.6}],"primary_tag":"SELL_RETURN_60","sell_streak":4},{"date":"2026-01-30","fund":"建信中证500指数增强A","code":"000478","category":"broad_index","action":"sell","unit":1,"buy_date":"2017-11-30","buy_adj":2.3535,"sell_adj":3.6726,"return_pct":56.0,"hold_days":2983,"tags":[{"rule_id":"SELL_RETURN_60","rule_name":"收益率≥60% 加大减仓","confidence":0.75},{"rule_id":"SELL_RESISTANCE","rule_name":"技术压力位减仓","confidence":0.6}],"primary_tag":"SELL_RETURN_60","sell_streak":6},{"date":"2026-03-06","fund":"华夏恒生ETF联接A","code":"000071","category":"overseas","action":"sell","unit":1,"buy_date":"2016-03-31","buy_adj":1.025,"sell_adj":1.5343,"return_pct":49.7,"hold_days":3627,"tags":[{"rule_id":"SELL_RESISTANCE","rule_name":"技术压力位减仓","confidence":0.6}],"primary_tag":"SELL_RESISTANCE","sell_streak":10},{"date":"2026-03-24","fund":"广发中证环保ETF联接A","code":"001064","category":"sector","action":"sell","unit":1,"buy_date":"2023-12-12","buy_adj":0.6889,"sell_adj":1.0125,"return_pct":47.0,"hold_days":833,"tags":[{"rule_id":"SELL_RESISTANCE","rule_name":"技术压力位减仓","confidence":0.6}],"primary_tag":"SELL_RESISTANCE","sell_streak":10},{"date":"2026-04-09","fund":"建信中证500指数增强A","code":"000478","category":"broad_index","action":"sell","unit":1,"buy_date":"2017-12-29","buy_adj":2.3536,"sell_adj":3.5055,"return_pct":48.9,"hold_days":3023,"tags":[{"rule_id":"SELL_RETURN_30","rule_name":"收益率≥30% 启动减仓","confidence":0.8},{"rule_id":"SELL_RESISTANCE","rule_name":"技术压力位减仓","confidence":0.6}],"primary_tag":"SELL_RETURN_30","sell_streak":7},{"date":"2026-04-10","fund":"华夏中证500ETF联接A","code":"001052","category":"broad_index","action":"sell","unit":1,"buy_date":"2018-05-31","buy_adj":0.619,"sell_adj":0.9525,"return_pct":53.9,"hold_days":2871,"tags":[{"rule_id":"SELL_RETURN_30","rule_name":"收益率≥30% 启动减仓","confidence":0.8},{"rule_id":"SELL_RESISTANCE","rule_name":"技术压力位减仓","confidence":0.6}],"primary_tag":"SELL_RETURN_30","sell_streak":5},{"date":"2026-04-15","fund":"华宝医疗ETF联接C","code":"012323","category":"sector","action":"sell","unit":1,"buy_date":"2023-06-07","buy_adj":0.7329,"sell_adj":0.5825,"return_pct":-20.5,"hold_days":1043,"tags":[{"rule_id":"SELL_MECHANICAL","rule_name":"机械执行（兜底标签）","confidence":0.3}],"primary_tag":"SELL_MECHANICAL","sell_streak":2},{"date":"2026-04-23","fund":"建信中证500指数增强A","code":"000478","category":"broad_index","action":"sell","unit":1,"buy_date":"2018-02-01","buy_adj":2.3075,"sell_adj":3.6694,"return_pct":59.0,"hold_days":3003,"tags":[{"rule_id":"SELL_RETURN_60","rule_name":"收益率≥60% 加大减仓","confidence":0.75},{"rule_id":"SELL_RESISTANCE","rule_name":"技术压力位减仓","confidence":0.6}],"primary_tag":"SELL_RETURN_60","sell_streak":8}],"predictions":[{"fund":"富国沪深300指数增强A","code":"100038","category":"broad_index","category_label":"宽基指数","data_quality":"complete","units":7,"avg_buy_nav":1.6645,"current_nav":2.002,"current_adj_nav":2.84341952,"return_pct":71.0,"return_m4_irr":70.82,"hold_days":2895,"days_since_buy":2650,"days_since_sell":null,"primary_signal":{"action":"sell","rule_id":"SELL_RETURN_60","rule_name":"收益率≥60% 加大减仓","confidence":0.95,"description":"宽基平均收益率达到 60%+，进入持续减仓阶段，每周/每月稳定卖出。","source":"21493 (2026-01-07): 把平均收益率60%以上的中证500分一些给别人"},"all_signals":[{"action":"sell","rule_id":"SELL_RETURN_60","rule_name":"收益率≥60% 加大减仓","confidence":0.95,"description":"宽基平均收益率达到 60%+，进入持续减仓阶段，每周/每月稳定卖出。","source":"21493 (2026-01-07): 把平均收益率60%以上的中证500分一些给别人"}],"next_threshold":{"type":"rolling_sell","next_action":"sell","description":"已在 60% 减仓阶段，按压力位/月度节奏持续卖出"}},{"fund":"富国中证500指数增强A","code":"161017","category":"broad_index","category_label":"宽基指数","data_quality":"complete","units":1,"avg_buy_nav":1.636,"current_nav":2.755,"current_adj_nav":3.91080397,"return_pct":105.8,"return_m4_irr":105.87,"hold_days":2833,"days_since_buy":2743,"days_since_sell":101,"primary_signal":{"action":"sell","rule_id":"SELL_RETURN_60","rule_name":"收益率≥60% 加大减仓","confidence":0.95,"description":"宽基平均收益率达到 60%+，进入持续减仓阶段，每周/每月稳定卖出。","source":"21493 (2026-01-07): 把平均收益率60%以上的中证500分一些给别人"},"all_signals":[{"action":"sell","rule_id":"SELL_RETURN_60","rule_name":"收益率≥60% 加大减仓","confidence":0.95,"description":"宽基平均收益率达到 60%+，进入持续减仓阶段，每周/每月稳定卖出。","source":"21493 (2026-01-07): 把平均收益率60%以上的中证500分一些给别人"}],"next_threshold":{"type":"rolling_sell","next_action":"sell","description":"已在 60% 减仓阶段，按压力位/月度节奏持续卖出"}},{"fund":"建信中证500指数增强A","code":"000478","category":"broad_index","category_label":"宽基指数","data_quality":"unit_only","units":4,"avg_buy_nav":2.1333,"current_nav":3.6897,"current_adj_nav":3.6897,"return_pct":50.5,"return_m4_irr":50.72,"hold_days":3293,"days_since_buy":2345,"days_since_sell":11,"primary_signal":{"action":"sell","rule_id":"SELL_RETURN_30","rule_name":"收益率≥30% 启动减仓","confidence":0.8,"description":"宽基收益率超过 30% 开始考虑首次减仓 1 份，标志性减仓节点。","source":"历史交易模式 (2021-09 中证500首卖 +37.4%, 2025-08 +30.4%)"},"all_signals":[{"action":"sell","rule_id":"SELL_RETURN_30","rule_name":"收益率≥30% 启动减仓","confidence":0.8,"description":"宽基收益率超过 30% 开始考虑首次减仓 1 份，标志性减仓节点。","source":"历史交易模式 (2021-09 中证500首卖 +37.4%, 2025-08 +30.4%)"}],"next_threshold":{"type":"return_threshold","next_action":"sell","description":"需再涨约 9.5% → 进入 60% 加大减仓阶段"}},{"fund":"华夏沪深300ETF联接A","code":"000051","category":"broad_index","category_label":"宽基指数","data_quality":"unit_only","units":2,"avg_buy_nav":1.3144,"current_nav":1.808,"current_adj_nav":1.808,"return_pct":52.2,"return_m4_irr":50.47,"hold_days":3626,"days_since_buy":1214,"days_since_sell":1921,"primary_signal":{"action":"sell","rule_id":"SELL_RETURN_30","rule_name":"收益率≥30% 启动减仓","confidence":0.8,"description":"宽基收益率超过 30% 开始考虑首次减仓 1 份，标志性减仓节点。","source":"历史交易模式 (2021-09 中证500首卖 +37.4%, 2025-08 +30.4%)"},"all_signals":[{"action":"sell","rule_id":"SELL_RETURN_30","rule_name":"收益率≥30% 启动减仓","confidence":0.8,"description":"宽基收益率超过 30% 开始考虑首次减仓 1 份，标志性减仓节点。","source":"历史交易模式 (2021-09 中证500首卖 +37.4%, 2025-08 +30.4%)"}],"next_threshold":{"type":"return_threshold","next_action":"sell","description":"需再涨约 7.8% → 进入 60% 加大减仓阶段"}},{"fund":"博时标普500ETF联接A","code":"050025","category":"broad_index","category_label":"宽基指数","data_quality":"complete","units":1,"avg_buy_nav":3.2635,"current_nav":5.2751,"current_adj_nav":5.53729357,"return_pct":36.9,"return_m4_irr":41.39,"hold_days":2237,"days_since_buy":1281,"days_since_sell":990,"primary_signal":{"action":"sell","rule_id":"SELL_RETURN_30","rule_name":"收益率≥30% 启动减仓","confidence":0.8,"description":"宽基收益率超过 30% 开始考虑首次减仓 1 份，标志性减仓节点。","source":"历史交易模式 (2021-09 中证500首卖 +37.4%, 2025-08 +30.4%)"},"all_signals":[{"action":"sell","rule_id":"SELL_RETURN_30","rule_name":"收益率≥30% 启动减仓","confidence":0.8,"description":"宽基收益率超过 30% 开始考虑首次减仓 1 份，标志性减仓节点。","source":"历史交易模式 (2021-09 中证500首卖 +37.4%, 2025-08 +30.4%)"}],"next_threshold":{"type":"return_threshold","next_action":"sell","description":"需再涨约 23.1% → 进入 60% 加大减仓阶段"}},{"fund":"华夏中证500ETF联接A","code":"001052","category":"broad_index","category_label":"宽基指数","data_quality":"unit_only","units":4,"avg_buy_nav":0.5212,"current_nav":0.9962,"current_adj_nav":0.9962,"return_pct":59.4,"return_m4_irr":59.7,"hold_days":3717,"days_since_buy":2712,"days_since_sell":24,"primary_signal":{"action":"sell","rule_id":"SELL_RETURN_60","rule_name":"收益率≥60% 加大减仓","confidence":0.75,"description":"宽基平均收益率达到 60%+，进入持续减仓阶段，每周/每月稳定卖出。","source":"21493 (2026-01-07): 把平均收益率60%以上的中证500分一些给别人"},"all_signals":[{"action":"sell","rule_id":"SELL_RETURN_60","rule_name":"收益率≥60% 加大减仓","confidence":0.75,"description":"宽基平均收益率达到 60%+，进入持续减仓阶段，每周/每月稳定卖出。","source":"21493 (2026-01-07): 把平均收益率60%以上的中证500分一些给别人"}],"next_threshold":{"type":"rolling_sell","next_action":"sell","description":"已在 60% 减仓阶段，按压力位/月度节奏持续卖出"}},{"fund":"华夏上证50ETF联接A","code":"001051","category":"broad_index","category_label":"宽基指数","data_quality":"complete","units":3,"avg_buy_nav":0.794,"current_nav":1.0952,"current_adj_nav":1.15135378,"return_pct":55.0,"return_m4_irr":55.52,"hold_days":3927,"days_since_buy":2782,"days_since_sell":245,"primary_signal":{"action":"sell","rule_id":"SELL_RETURN_60","rule_name":"收益率≥60% 加大减仓","confidence":0.75,"description":"宽基平均收益率达到 60%+，进入持续减仓阶段，每周/每月稳定卖出。","source":"21493 (2026-01-07): 把平均收益率60%以上的中证500分一些给别人"},"all_signals":[{"action":"sell","rule_id":"SELL_RETURN_60","rule_name":"收益率≥60% 加大减仓","confidence":0.75,"description":"宽基平均收益率达到 60%+，进入持续减仓阶段，每周/每月稳定卖出。","source":"21493 (2026-01-07): 把平均收益率60%以上的中证500分一些给别人"}],"next_threshold":{"type":"rolling_sell","next_action":"sell","description":"已在 60% 减仓阶段，按压力位/月度节奏持续卖出"}},{"fund":"广发医药卫生联接A","code":"001180","category":"sector","category_label":"行业指数","data_quality":"unit_only","units":7,"avg_buy_nav":0.827,"current_nav":0.8018,"current_adj_nav":0.8018,"return_pct":13.5,"return_m4_irr":15.03,"hold_days":3428,"days_since_buy":1043,"days_since_sell":2061,"primary_signal":{"action":"sell","rule_id":"SELL_GRID_PROFIT","rule_name":"网格波段获利","confidence":0.55,"description":"波动大的不死品种，跌X%买，涨X%卖，每格留利润。","source":"66685 (2026-02-07): 网格波段适合波动巨大的不死品种"},"all_signals":[{"action":"sell","rule_id":"SELL_GRID_PROFIT","rule_name":"网格波段获利","confidence":0.55,"description":"波动大的不死品种，跌X%买，涨X%卖，每格留利润。","source":"66685 (2026-02-07): 网格波段适合波动巨大的不死品种"}],"next_threshold":{"type":"wait","next_action":"hold","description":"等待估值进一步偏离均值"}},{"fund":"融通健康产业灵活配置混合A","code":"000727","category":"sector","category_label":"行业指数","data_quality":"unit_only","units":1,"avg_buy_nav":2.922,"current_nav":2.684,"current_adj_nav":2.684,"return_pct":9.9,"return_m4_irr":10.55,"hold_days":1319,"days_since_buy":1001,"days_since_sell":1264,"primary_signal":{"action":"sell","rule_id":"SELL_GRID_PROFIT","rule_name":"网格波段获利","confidence":0.55,"description":"波动大的不死品种，跌X%买，涨X%卖，每格留利润。","source":"66685 (2026-02-07): 网格波段适合波动巨大的不死品种"},"all_signals":[{"action":"sell","rule_id":"SELL_GRID_PROFIT","rule_name":"网格波段获利","confidence":0.55,"description":"波动大的不死品种，跌X%买，涨X%卖，每格留利润。","source":"66685 (2026-02-07): 网格波段适合波动巨大的不死品种"}],"next_threshold":{"type":"wait","next_action":"hold","description":"等待估值进一步偏离均值"}},{"fund":"易方达消费行业","code":"110022","category":"sector","category_label":"行业指数","data_quality":"unit_only","units":1,"avg_buy_nav":3.121,"current_nav":3.133,"current_adj_nav":3.133,"return_pct":18.5,"return_m4_irr":13.83,"hold_days":2743,"days_since_buy":41,"days_since_sell":1214,"primary_signal":{"action":"sell","rule_id":"SELL_GRID_PROFIT","rule_name":"网格波段获利","confidence":0.55,"description":"波动大的不死品种，跌X%买，涨X%卖，每格留利润。","source":"66685 (2026-02-07): 网格波段适合波动巨大的不死品种"},"all_signals":[{"action":"sell","rule_id":"SELL_GRID_PROFIT","rule_name":"网格波段获利","confidence":0.55,"description":"波动大的不死品种，跌X%买，涨X%卖，每格留利润。","source":"66685 (2026-02-07): 网格波段适合波动巨大的不死品种"}],"next_threshold":{"type":"grid_sell","next_action":"sell","description":"波段获利出局，留利润给下一格"}},{"fund":"富国中证红利指数增强A","code":"100032","category":"dividend","category_label":"红利/低波","data_quality":"complete","units":13,"avg_buy_nav":3.2613,"current_nav":1.011,"current_adj_nav":5.79381581,"return_pct":76.7,"return_m4_irr":76.53,"hold_days":3428,"days_since_buy":2195,"days_since_sell":788,"primary_signal":{"action":"buy","rule_id":"BUY_DIVIDEND_MONTHLY","rule_name":"红利每月持续买入","confidence":0.7,"description":"S计划红利每月至少买1份，承受短期下跌、坚持纪律持续投入。","source":"73435 (2026-04-15): 估值不低也要继续买入红利"},"all_signals":[{"action":"buy","rule_id":"BUY_DIVIDEND_MONTHLY","rule_name":"红利每月持续买入","confidence":0.7,"description":"S计划红利每月至少买1份，承受短期下跌、坚持纪律持续投入。","source":"73435 (2026-04-15): 估值不低也要继续买入红利"}],"next_threshold":{"type":"monthly_buy","next_action":"buy","description":"距下次月度买入约 0 天（红利每月至少买 1 份）"}},{"fund":"大摩健康产业混合A","code":"002708","category":"sector","category_label":"行业指数","data_quality":"unit_only","units":4,"avg_buy_nav":2.3872,"current_nav":1.717,"current_adj_nav":1.717,"return_pct":-27.7,"return_m4_irr":-28.08,"hold_days":1481,"days_since_buy":1057,"days_since_sell":null,"primary_signal":{"action":"buy","rule_id":"BUY_VALUATION_LOW","rule_name":"估值历史低位建仓","confidence":0.7,"description":"行业指数跌至估值历史低位（如医药 PB 2008-10 以来最低），开始建仓。","source":"71383 (2026-03-23): 全指医药估值历史第二低"},"all_signals":[{"action":"buy","rule_id":"BUY_VALUATION_LOW","rule_name":"估值历史低位建仓","confidence":0.7,"description":"行业指数跌至估值历史低位（如医药 PB 2008-10 以来最低），开始建仓。","source":"71383 (2026-03-23): 全指医药估值历史第二低"},{"action":"buy","rule_id":"BUY_LEFT_SIDE_GRID","rule_name":"左侧分批买入（空间维度）","confidence":0.5,"description":"下跌 5%/7%/10% 加仓，避免筹码聚集在下跌高位。空间策略。","source":"WX-2021-09-27: 我的左侧买入节奏"}],"next_threshold":{"type":"grid_buy","next_action":"buy","description":"处于建仓波段，每 5-7% 跌幅加一份"}},{"fund":"交银施罗德中证海外中国互联网指数(QDII-LOF)A","code":"164906","category":"overseas","category_label":"海外/QDII","data_quality":"unit_only","units":4,"avg_buy_nav":1.615,"current_nav":1.0187,"current_adj_nav":1.0187,"return_pct":-8.9,"return_m4_irr":-7.28,"hold_days":2799,"days_since_buy":1655,"days_since_sell":2000,"primary_signal":{"action":"buy","rule_id":"BUY_LEFT_SIDE_GRID","rule_name":"左侧分批买入（空间维度）","confidence":0.5,"description":"下跌 5%/7%/10% 加仓，避免筹码聚集在下跌高位。空间策略。","source":"WX-2021-09-27: 我的左侧买入节奏"},"all_signals":[{"action":"buy","rule_id":"BUY_LEFT_SIDE_GRID","rule_name":"左侧分批买入（空间维度）","confidence":0.5,"description":"下跌 5%/7%/10% 加仓，避免筹码聚集在下跌高位。空间策略。","source":"WX-2021-09-27: 我的左侧买入节奏"}],"next_threshold":{"type":"watch","next_action":"hold","description":"海外配置以分散为主，按计划微调"}},{"fund":"华宝医疗ETF联接C","code":"012323","category":"sector","category_label":"行业指数","data_quality":"unit_only","units":4,"avg_buy_nav":0.6059,"current_nav":0.58,"current_adj_nav":0.58,"return_pct":-8.9,"return_m4_irr":-9.68,"hold_days":1104,"days_since_buy":42,"days_since_sell":19,"primary_signal":{"action":"buy","rule_id":"BUY_LEFT_SIDE_GRID","rule_name":"左侧分批买入（空间维度）","confidence":0.5,"description":"下跌 5%/7%/10% 加仓，避免筹码聚集在下跌高位。空间策略。","source":"WX-2021-09-27: 我的左侧买入节奏"},"all_signals":[{"action":"buy","rule_id":"BUY_LEFT_SIDE_GRID","rule_name":"左侧分批买入（空间维度）","confidence":0.5,"description":"下跌 5%/7%/10% 加仓，避免筹码聚集在下跌高位。空间策略。","source":"WX-2021-09-27: 我的左侧买入节奏"}],"next_threshold":{"type":"wait","next_action":"hold","description":"等待估值进一步偏离均值"}},{"fund":"华宝医疗ETF联接A","code":"162412","category":"sector","category_label":"行业指数","data_quality":"complete","units":3,"avg_buy_nav":0.4618,"current_nav":0.5857,"current_adj_nav":0.37286969,"return_pct":-19.1,"return_m4_irr":-19.26,"hold_days":1090,"days_since_buy":986,"days_since_sell":null,"primary_signal":{"action":"buy","rule_id":"BUY_LEFT_SIDE_GRID","rule_name":"左侧分批买入（空间维度）","confidence":0.5,"description":"下跌 5%/7%/10% 加仓，避免筹码聚集在下跌高位。空间策略。","source":"WX-2021-09-27: 我的左侧买入节奏"},"all_signals":[{"action":"buy","rule_id":"BUY_LEFT_SIDE_GRID","rule_name":"左侧分批买入（空间维度）","confidence":0.5,"description":"下跌 5%/7%/10% 加仓，避免筹码聚集在下跌高位。空间策略。","source":"WX-2021-09-27: 我的左侧买入节奏"}],"next_threshold":{"type":"grid_buy","next_action":"buy","description":"处于建仓波段，每 5-7% 跌幅加一份"}},{"fund":"富国消费主题混合C","code":"011309","category":"sector","category_label":"行业指数","data_quality":"unit_only","units":3,"avg_buy_nav":2.1543,"current_nav":1.939,"current_adj_nav":1.939,"return_pct":-7.8,"return_m4_irr":-7.75,"hold_days":1074,"days_since_buy":614,"days_since_sell":728,"primary_signal":{"action":"buy","rule_id":"BUY_LEFT_SIDE_GRID","rule_name":"左侧分批买入（空间维度）","confidence":0.5,"description":"下跌 5%/7%/10% 加仓，避免筹码聚集在下跌高位。空间策略。","source":"WX-2021-09-27: 我的左侧买入节奏"},"all_signals":[{"action":"buy","rule_id":"BUY_LEFT_SIDE_GRID","rule_name":"左侧分批买入（空间维度）","confidence":0.5,"description":"下跌 5%/7%/10% 加仓，避免筹码聚集在下跌高位。空间策略。","source":"WX-2021-09-27: 我的左侧买入节奏"}],"next_threshold":{"type":"wait","next_action":"hold","description":"等待估值进一步偏离均值"}},{"fund":"富国消费主题混合A","code":"519915","category":"sector","category_label":"行业指数","data_quality":"unit_only","units":3,"avg_buy_nav":2.2493,"current_nav":2.001,"current_adj_nav":2.001,"return_pct":-7.5,"return_m4_irr":-7.39,"hold_days":1704,"days_since_buy":593,"days_since_sell":1166,"primary_signal":{"action":"buy","rule_id":"BUY_LEFT_SIDE_GRID","rule_name":"左侧分批买入（空间维度）","confidence":0.5,"description":"下跌 5%/7%/10% 加仓，避免筹码聚集在下跌高位。空间策略。","source":"WX-2021-09-27: 我的左侧买入节奏"},"all_signals":[{"action":"buy","rule_id":"BUY_LEFT_SIDE_GRID","rule_name":"左侧分批买入（空间维度）","confidence":0.5,"description":"下跌 5%/7%/10% 加仓，避免筹码聚集在下跌高位。空间策略。","source":"WX-2021-09-27: 我的左侧买入节奏"}],"next_threshold":{"type":"wait","next_action":"hold","description":"等待估值进一步偏离均值"}},{"fund":"易方达中证海外联接人民币A","code":"006327","category":"overseas","category_label":"海外/QDII","data_quality":"unit_only","units":2,"avg_buy_nav":1.0423,"current_nav":0.9456,"current_adj_nav":0.9456,"return_pct":-9.2,"return_m4_irr":-9.27,"hold_days":1680,"days_since_buy":59,"days_since_sell":null,"primary_signal":{"action":"buy","rule_id":"BUY_LEFT_SIDE_GRID","rule_name":"左侧分批买入（空间维度）","confidence":0.5,"description":"下跌 5%/7%/10% 加仓，避免筹码聚集在下跌高位。空间策略。","source":"WX-2021-09-27: 我的左侧买入节奏"},"all_signals":[{"action":"buy","rule_id":"BUY_LEFT_SIDE_GRID","rule_name":"左侧分批买入（空间维度）","confidence":0.5,"description":"下跌 5%/7%/10% 加仓，避免筹码聚集在下跌高位。空间策略。","source":"WX-2021-09-27: 我的左侧买入节奏"}],"next_threshold":{"type":"watch","next_action":"hold","description":"海外配置以分散为主，按计划微调"}},{"fund":"汇添富中证主要消费ETF联接A","code":"000248","category":"sector","category_label":"行业指数","data_quality":"unit_only","units":1,"avg_buy_nav":2.1835,"current_nav":2.0391,"current_adj_nav":2.0391,"return_pct":-6.6,"return_m4_irr":-6.61,"hold_days":117,"days_since_buy":117,"days_since_sell":null,"primary_signal":{"action":"buy","rule_id":"BUY_LEFT_SIDE_GRID","rule_name":"左侧分批买入（空间维度）","confidence":0.5,"description":"下跌 5%/7%/10% 加仓，避免筹码聚集在下跌高位。空间策略。","source":"WX-2021-09-27: 我的左侧买入节奏"},"all_signals":[{"action":"buy","rule_id":"BUY_LEFT_SIDE_GRID","rule_name":"左侧分批买入（空间维度）","confidence":0.5,"description":"下跌 5%/7%/10% 加仓，避免筹码聚集在下跌高位。空间策略。","source":"WX-2021-09-27: 我的左侧买入节奏"}],"next_threshold":{"type":"wait","next_action":"hold","description":"等待估值进一步偏离均值"}},{"fund":"广发养老指数A","code":"000968","category":"unknown","category_label":"其他","data_quality":"unit_only","units":7,"avg_buy_nav":0.9288,"current_nav":0.8802,"current_adj_nav":0.8802,"return_pct":7.3,"return_m4_irr":8.66,"hold_days":3751,"days_since_buy":2685,"days_since_sell":2061,"primary_signal":{"action":"hold","rule_id":"HOLD","rule_name":"继续持有/观望","confidence":0.5,"description":"无明显触发信号，按节奏等待。","source":""},"all_signals":[],"next_threshold":{"type":"unknown","next_action":"hold","description":""}},{"fund":"华夏恒生ETF联接A","code":"000071","category":"overseas","category_label":"海外/QDII","data_quality":"unit_only","units":7,"avg_buy_nav":1.2513,"current_nav":1.5268,"current_adj_nav":1.5268,"return_pct":31.2,"return_m4_irr":30.69,"hold_days":3899,"days_since_buy":1511,"days_since_sell":59,"primary_signal":{"action":"hold","rule_id":"HOLD","rule_name":"继续持有/观望","confidence":0.5,"description":"无明显触发信号，按节奏等待。","source":""},"all_signals":[],"next_threshold":{"type":"watch","next_action":"hold","description":"海外配置以分散为主，按计划微调"}},{"fund":"兴全可转债混合","code":"340001","category":"convertible","category_label":"可转债/混合","data_quality":"complete","units":4,"avg_buy_nav":7.2683,"current_nav":1.168,"current_adj_nav":13.70944638,"return_pct":81.9,"return_m4_irr":82.18,"hold_days":2895,"days_since_buy":2712,"days_since_sell":1526,"primary_signal":{"action":"hold","rule_id":"HOLD","rule_name":"继续持有/观望","confidence":0.5,"description":"无明显触发信号，按节奏等待。","source":""},"all_signals":[],"next_threshold":{"type":"unknown","next_action":"hold","description":""}},{"fund":"易方达安心债券A","code":"110027","category":"unknown","category_label":"其他","data_quality":"complete","units":3,"avg_buy_nav":2.8165,"current_nav":2.2787,"current_adj_nav":4.35770025,"return_pct":44.4,"return_m4_irr":45.0,"hold_days":2650,"days_since_buy":2469,"days_since_sell":1481,"primary_signal":{"action":"hold","rule_id":"HOLD","rule_name":"继续持有/观望","confidence":0.5,"description":"无明显触发信号，按节奏等待。","source":""},"all_signals":[],"next_threshold":{"type":"unknown","next_action":"hold","description":""}},{"fund":"天弘恒生科技指数联接(QDII)A","code":"012348","category":"overseas","category_label":"海外/QDII","data_quality":"unit_only","units":3,"avg_buy_nav":0.6259,"current_nav":0.6718,"current_adj_nav":0.6718,"return_pct":8.0,"return_m4_irr":8.04,"hold_days":1600,"days_since_buy":392,"days_since_sell":376,"primary_signal":{"action":"hold","rule_id":"HOLD","rule_name":"继续持有/观望","confidence":0.5,"description":"无明显触发信号，按节奏等待。","source":""},"all_signals":[],"next_threshold":{"type":"watch","next_action":"hold","description":"海外配置以分散为主，按计划微调"}},{"fund":"广发全球医疗保健(QDII)(人民币)A","code":"000369","category":"overseas","category_label":"海外/QDII","data_quality":"complete","units":2,"avg_buy_nav":2.4981,"current_nav":2.317,"current_adj_nav":2.55211989,"return_pct":2.2,"return_m4_irr":2.16,"hold_days":858,"days_since_buy":284,"days_since_sell":null,"primary_signal":{"action":"hold","rule_id":"HOLD","rule_name":"继续持有/观望","confidence":0.5,"description":"无明显触发信号，按节奏等待。","source":""},"all_signals":[],"next_threshold":{"type":"watch","next_action":"hold","description":"海外配置以分散为主，按计划微调"}},{"fund":"富国全球债券(QDII)人民币A","code":"100050","category":"overseas","category_label":"海外/QDII","data_quality":"complete","units":2,"avg_buy_nav":1.3543,"current_nav":1.2795,"current_adj_nav":1.35953294,"return_pct":0.4,"return_m4_irr":0.39,"hold_days":556,"days_since_buy":62,"days_since_sell":null,"primary_signal":{"action":"hold","rule_id":"HOLD","rule_name":"继续持有/观望","confidence":0.5,"description":"无明显触发信号，按节奏等待。","source":""},"all_signals":[],"next_threshold":{"type":"watch","next_action":"hold","description":"海外配置以分散为主，按计划微调"}},{"fund":"博时中证红利低波动100ETF联接A","code":"021550","category":"dividend","category_label":"红利/低波","data_quality":"complete","units":2,"avg_buy_nav":1.1941,"current_nav":1.1352,"current_adj_nav":1.20544733,"return_pct":0.9,"return_m4_irr":0.95,"hold_days":140,"days_since_buy":18,"days_since_sell":null,"primary_signal":{"action":"hold","rule_id":"HOLD","rule_name":"继续持有/观望","confidence":0.5,"description":"无明显触发信号，按节奏等待。","source":""},"all_signals":[],"next_threshold":{"type":"monthly_buy","next_action":"buy","description":"距下次月度买入约 12 天（红利每月至少买 1 份）"}},{"fund":"广发中债7-10年国开债指数A","code":"003376","category":"bond","category_label":"债券/固收","data_quality":"complete","units":1,"avg_buy_nav":1.2572,"current_nav":1.3619,"current_adj_nav":1.50023605,"return_pct":10.0,"return_m4_irr":10.34,"hold_days":3366,"days_since_buy":1243,"days_since_sell":1434,"primary_signal":{"action":"hold","rule_id":"HOLD","rule_name":"继续持有/观望","confidence":0.5,"description":"无明显触发信号，按节奏等待。","source":""},"all_signals":[],"next_threshold":{"type":"defensive","next_action":"hold","description":"防守仓位，维持 3 年提款额"}},{"fund":"汇添富美元债债券人民币A","code":"004419","category":"bond","category_label":"债券/固收","data_quality":"unit_only","units":1,"avg_buy_nav":1.054,"current_nav":1.0463,"current_adj_nav":1.0463,"return_pct":-0.7,"return_m4_irr":-0.73,"hold_days":602,"days_since_buy":602,"days_since_sell":null,"primary_signal":{"action":"hold","rule_id":"HOLD","rule_name":"继续持有/观望","confidence":0.5,"description":"无明显触发信号，按节奏等待。","source":""},"all_signals":[],"next_threshold":{"type":"defensive","next_action":"hold","description":"防守仓位，维持 3 年提款额"}},{"fund":"富国全球债券(QDII)人民币C","code":"019518","category":"overseas","category_label":"海外/QDII","data_quality":"complete","units":1,"avg_buy_nav":1.3244,"current_nav":1.2707,"current_adj_nav":1.35031758,"return_pct":2.0,"return_m4_irr":1.96,"hold_days":550,"days_since_buy":550,"days_since_sell":null,"primary_signal":{"action":"hold","rule_id":"HOLD","rule_name":"继续持有/观望","confidence":0.5,"description":"无明显触发信号，按节奏等待。","source":""},"all_signals":[],"next_threshold":{"type":"watch","next_action":"hold","description":"海外配置以分散为主，按计划微调"}},{"fund":"易方达中证全指证券公司指数(LOF)A","code":"502010","category":"sector","category_label":"行业指数","data_quality":"complete","units":1,"avg_buy_nav":0.4604,"current_nav":1.2488,"current_adj_nav":0.85404127,"return_pct":49.7,"return_m4_irr":48.68,"hold_days":3063,"days_since_buy":2758,"days_since_sell":539,"primary_signal":{"action":"hold","rule_id":"HOLD","rule_name":"继续持有/观望","confidence":0.5,"description":"无明显触发信号，按节奏等待。","source":""},"all_signals":[],"next_threshold":{"type":"grid_sell","next_action":"sell","description":"波段获利出局，留利润给下一格"}},{"fund":"中银美元债债券人民币A","code":"002286","category":"bond","category_label":"债券/固收","data_quality":"unit_only","units":1,"avg_buy_nav":1.2259,"current_nav":1.2133,"current_adj_nav":1.2133,"return_pct":-1.0,"return_m4_irr":-1.03,"hold_days":294,"days_since_buy":294,"days_since_sell":null,"primary_signal":{"action":"hold","rule_id":"HOLD","rule_name":"继续持有/观望","confidence":0.5,"description":"无明显触发信号，按节奏等待。","source":""},"all_signals":[],"next_threshold":{"type":"defensive","next_action":"hold","description":"防守仓位，维持 3 年提款额"}},{"fund":"广发中证全指金融地产联接A","code":"001469","category":"sector","category_label":"行业指数","data_quality":"unit_only","units":1,"avg_buy_nav":1.1746,"current_nav":1.2434,"current_adj_nav":1.2434,"return_pct":25.9,"return_m4_irr":25.24,"hold_days":2881,"days_since_buy":1939,"days_since_sell":294,"primary_signal":{"action":"hold","rule_id":"HOLD","rule_name":"继续持有/观望","confidence":0.5,"description":"无明显触发信号，按节奏等待。","source":""},"all_signals":[],"next_threshold":{"type":"grid_sell","next_action":"sell","description":"波段获利出局，留利润给下一格"}},{"fund":"广发中债1-3年国开债A","code":"006484","category":"bond","category_label":"债券/固收","data_quality":"complete","units":1,"avg_buy_nav":1.2447,"current_nav":1.0606,"current_adj_nav":1.25795095,"return_pct":1.1,"return_m4_irr":1.07,"hold_days":242,"days_since_buy":242,"days_since_sell":null,"primary_signal":{"action":"hold","rule_id":"HOLD","rule_name":"继续持有/观望","confidence":0.5,"description":"无明显触发信号，按节奏等待。","source":""},"all_signals":[],"next_threshold":{"type":"defensive","next_action":"hold","description":"防守仓位，维持 3 年提款额"}},{"fund":"景顺长城景泰纯利债券A","code":"007562","category":"unknown","category_label":"其他","data_quality":"complete","units":1,"avg_buy_nav":1.3367,"current_nav":1.2081,"current_adj_nav":1.33969276,"return_pct":0.2,"return_m4_irr":0.22,"hold_days":24,"days_since_buy":24,"days_since_sell":null,"primary_signal":{"action":"hold","rule_id":"HOLD","rule_name":"继续持有/观望","confidence":0.5,"description":"无明显触发信号，按节奏等待。","source":""},"all_signals":[],"next_threshold":{"type":"unknown","next_action":"hold","description":""}}],"stats":{"total_tagged":147,"tag_distribution":{"SELL_MECHANICAL":46,"SELL_RESISTANCE":70,"SELL_RETURN_30":14,"SELL_RETURN_60":13,"SELL_GRID_PROFIT":4},"signal_distribution":{"SELL_RETURN_60":4,"SELL_RETURN_30":3,"SELL_GRID_PROFIT":3,"BUY_DIVIDEND_MONTHLY":1,"BUY_VALUATION_LOW":1,"BUY_LEFT_SIDE_GRID":7,"HOLD":16}}}